{
  "id": 10000069,
  "rank": 5,
  "name": "提纳里",
  "element": "Grass",
  "weaponType": "WEAPON_BOW",
  "icon": "UI_AvatarIcon_Tighnari",
  "birthday": [
    12,
    29
  ],
  "release": 1661288400,
  "route": "Tighnari",
  "fetter": {
    "title": "浅蔚轻行",
    "detail": "精通植物学的少年学者，现于道成林任巡林官一职。直率热忱，擅长教导脑瓜糊涂的人。",
    "constellation": "郭狐座",
    "native": "化城郭",
    "cv": {
      "EN": "艾利奥特·金迪",
      "CHS": "莫然",
      "JP": "小林沙苗",
      "KR": "郑义宅"
    }
  },
  "upgrade": {
    "prop": [
      {
        "propType": "FIGHT_PROP_BASE_HP",
        "initValue": 844.64154,
        "type": "GROW_CURVE_HP_S5"
      },
      {
        "propType": "FIGHT_PROP_BASE_ATTACK",
        "initValue": 20.8544,
        "type": "GROW_CURVE_ATTACK_S5"
      },
      {
        "propType": "FIGHT_PROP_BASE_DEFENSE",
        "initValue": 49.0606,
        "type": "GROW_CURVE_HP_S5"
      }
    ],
    "promote": [
      {
        "unlockMaxLevel": 20,
        "promoteLevel": 0
      },
      {
        "promoteLevel": 1,
        "costItems": {
          "101215": 3,
          "104131": 1,
          "112059": 3
        },
        "unlockMaxLevel": 40,
        "addProps": {
          "FIGHT_PROP_BASE_HP": 724.20374,
          "FIGHT_PROP_BASE_DEFENSE": 42.066,
          "FIGHT_PROP_BASE_ATTACK": 17.87946,
          "FIGHT_PROP_GRASS_ADD_HURT": 0
        },
        "requiredPlayerLevel": 15,
        "coinCost": 20000
      },
      {
        "promoteLevel": 2,
        "costItems": {
          "101215": 10,
          "104132": 3,
          "112059": 15,
          "113036": 2
        },
        "unlockMaxLevel": 50,
        "addProps": {
          "FIGHT_PROP_BASE_HP": 1238.76953,
          "FIGHT_PROP_BASE_DEFENSE": 71.955,
          "FIGHT_PROP_BASE_ATTACK": 30.58328,
          "FIGHT_PROP_GRASS_ADD_HURT": 0.072
        },
        "requiredPlayerLevel": 25,
        "coinCost": 40000
      },
      {
        "promoteLevel": 3,
        "costItems": {
          "101215": 20,
          "104132": 6,
          "112060": 12,
          "113036": 4
        },
        "unlockMaxLevel": 60,
        "addProps": {
          "FIGHT_PROP_BASE_HP": 1924.8573,
          "FIGHT_PROP_BASE_DEFENSE": 111.807,
          "FIGHT_PROP_BASE_ATTACK": 47.52171,
          "FIGHT_PROP_GRASS_ADD_HURT": 0.144
        },
        "requiredPlayerLevel": 30,
        "coinCost": 60000
      },
      {
        "promoteLevel": 4,
        "costItems": {
          "101215": 30,
          "104133": 3,
          "112060": 18,
          "113036": 8
        },
        "unlockMaxLevel": 70,
        "addProps": {
          "FIGHT_PROP_BASE_HP": 2439.4231,
          "FIGHT_PROP_BASE_DEFENSE": 141.696,
          "FIGHT_PROP_BASE_ATTACK": 60.22554,
          "FIGHT_PROP_GRASS_ADD_HURT": 0.144
        },
        "requiredPlayerLevel": 35,
        "coinCost": 80000
      },
      {
        "promoteLevel": 5,
        "costItems": {
          "101215": 45,
          "104133": 6,
          "112061": 12,
          "113036": 12
        },
        "unlockMaxLevel": 80,
        "addProps": {
          "FIGHT_PROP_BASE_HP": 2953.98901,
          "FIGHT_PROP_BASE_DEFENSE": 171.58501,
          "FIGHT_PROP_BASE_ATTACK": 72.92936,
          "FIGHT_PROP_GRASS_ADD_HURT": 0.216
        },
        "requiredPlayerLevel": 40,
        "coinCost": 100000
      },
      {
        "promoteLevel": 6,
        "costItems": {
          "101215": 60,
          "104134": 6,
          "112061": 24,
          "113036": 20
        },
        "unlockMaxLevel": 90,
        "addProps": {
          "FIGHT_PROP_BASE_HP": 3468.55469,
          "FIGHT_PROP_BASE_DEFENSE": 201.474,
          "FIGHT_PROP_BASE_ATTACK": 85.63319,
          "FIGHT_PROP_GRASS_ADD_HURT": 0.288
        },
        "requiredPlayerLevel": 50,
        "coinCost": 120000
      }
    ]
  },
  "other": {
    "nameCard": {
      "id": 210124,
      "name": "提纳里·沐露",
      "description": "名片纹饰。\\n提纳里用花露精心调制的精油，用来保养毛茸茸的大尾巴，淡淡的清香有着安神的功效。",
      "icon": "UI_NameCardIcon_Tighnari"
    },
    "specialFood": {
      "id": 108436,
      "name": "巡林官精选",
      "rank": 2,
      "effectIcon": "UI_Buff_Item_Def_Add",
      "icon": "UI_ItemIcon_108436"
    }
  },
  "ascension": {
    "101215": 1,
    "104131": 2,
    "104132": 3,
    "104133": 4,
    "104134": 5,
    "104319": 5,
    "104329": 2,
    "104330": 3,
    "104331": 4,
    "112059": 1,
    "112060": 2,
    "112061": 3,
    "113034": 5,
    "113036": 4
  },
  "talent": {
    "0": {
      "type": 0,
      "name": "普通攻击·藏蕴破障",
      "description": "<color=#FFD780FF>普通攻击<\/color>\\n进行至多四段的连续弓箭射击。\\n\\n<color=#FFD780FF>重击<\/color>\\n进行伤害更高、更为精准的<color=#FFD780FF>瞄准射击<\/color>。\\n瞄准时，草木的力量会在箭矢上持续积聚，并随攻击发射出去。根据蓄力时间长短，能造成不同的效果：\\n·一段蓄力：射出附有草元素的箭矢，造成<color=#99FF88FF>草元素伤害<\/color>；\\n·二段蓄力：发射花筥箭，造成<color=#99FF88FF>草元素伤害<\/color>。命中后，将产生4枚会自行追踪附近敌人的藏蕴花矢，能够造成<color=#99FF88FF>草元素伤害<\/color>。\\n\\n<color=#FFD780FF>下落攻击<\/color>\\n从空中射出箭雨，并迅速下坠冲击地面，在落地时造成范围伤害。",
      "icon": "Skill_A_02",
      "promote": {
        "1": {
          "level": 1,
          "costItems": null,
          "coinCost": null,
          "description": [
            "一段伤害|{param1:F1P}",
            "二段伤害|{param2:F1P}",
            "三段伤害|{param3:F1P}*2",
            "四段伤害|{param4:F1P}",
            "瞄准射击|{param5:F1P}",
            "一段蓄力瞄准射击|{param6:P}",
            "花筥箭伤害|{param7:F1P}",
            "藏蕴花矢伤害|{param8:F1P}",
            "下坠期间伤害|{param9:F1P}",
            "低空\/高空坠地冲击伤害|{param10:P}\/{param11:P}",
            "",
            "",
            "",
            "",
            "",
            ""
          ],
          "params": [
            0.44634,
            0.41968,
            0.26445,
            0.68628,
            0.4386,
            1.24,
            0.872,
            0.386,
            0.56829,
            1.13634,
            1.41934,
            0,
            0,
            0,
            0,
            0,
            0,
            0,
            0,
            0
          ]
        },
        "2": {
          "level": 2,
          "costItems": {
            "104329": 3,
            "112059": 6
          },
          "coinCost": 12500,
          "description": [
            "一段伤害|{param1:F1P}",
            "二段伤害|{param2:F1P}",
            "三段伤害|{param3:F1P}*2",
            "四段伤害|{param4:F1P}",
            "瞄准射击|{param5:F1P}",
            "一段蓄力瞄准射击|{param6:P}",
            "花筥箭伤害|{param7:F1P}",
            "藏蕴花矢伤害|{param8:F1P}",
            "下坠期间伤害|{param9:F1P}",
            "低空\/高空坠地冲击伤害|{param10:P}\/{param11:P}",
            "",
            "",
            "",
            "",
            "",
            ""
          ],
          "params": [
            0.48267,
            0.45384,
            0.28598,
            0.74214,
            0.4743,
            1.333,
            0.9374,
            0.41495,
            0.61454,
            1.22883,
            1.53487,
            0,
            0,
            0,
            0,
            0,
            0,
            0,
            0,
            0
          ]
        },
        "3": {
          "level": 3,
          "costItems": {
            "104330": 2,
            "112060": 3
          },
          "coinCost": 17500,
          "description": [
            "一段伤害|{param1:F1P}",
            "二段伤害|{param2:F1P}",
            "三段伤害|{param3:F1P}*2",
            "四段伤害|{param4:F1P}",
            "瞄准射击|{param5:F1P}",
            "一段蓄力瞄准射击|{param6:P}",
            "花筥箭伤害|{param7:F1P}",
            "藏蕴花矢伤害|{param8:F1P}",
            "下坠期间伤害|{param9:F1P}",
            "低空\/高空坠地冲击伤害|{param10:P}\/{param11:P}",
            "",
            "",
            "",
            "",
            "",
            ""
          ],
          "params": [
            0.519,
            0.488,
            0.3075,
            0.798,
            0.51,
            1.426,
            1.0028,
            0.4439,
            0.6608,
            1.32132,
            1.6504,
            0,
            0,
            0,
            0,
            0,
            0,
            0,
            0,
            0
          ]
        },
        "4": {
          "level": 4,
          "costItems": {
            "104330": 4,
            "112060": 4
          },
          "coinCost": 25000,
          "description": [
            "一段伤害|{param1:F1P}",
            "二段伤害|{param2:F1P}",
            "三段伤害|{param3:F1P}*2",
            "四段伤害|{param4:F1P}",
            "瞄准射击|{param5:F1P}",
            "一段蓄力瞄准射击|{param6:P}",
            "花筥箭伤害|{param7:F1P}",
            "藏蕴花矢伤害|{param8:F1P}",
            "下坠期间伤害|{param9:F1P}",
            "低空\/高空坠地冲击伤害|{param10:P}\/{param11:P}",
            "",
            "",
            "",
            "",
            "",
            ""
          ],
          "params": [
            0.5709,
            0.5368,
            0.33825,
            0.8778,
            0.561,
            1.55,
            1.09,
            0.4825,
            0.72688,
            1.45345,
            1.81544,
            0,
            0,
            0,
            0,
            0,
            0,
            0,
            0,
            0
          ]
        },
        "5": {
          "level": 5,
          "costItems": {
            "104330": 6,
            "112060": 6
          },
          "coinCost": 30000,
          "description": [
            "一段伤害|{param1:F1P}",
            "二段伤害|{param2:F1P}",
            "三段伤害|{param3:F1P}*2",
            "四段伤害|{param4:F1P}",
            "瞄准射击|{param5:F1P}",
            "一段蓄力瞄准射击|{param6:P}",
            "花筥箭伤害|{param7:F1P}",
            "藏蕴花矢伤害|{param8:F1P}",
            "下坠期间伤害|{param9:F1P}",
            "低空\/高空坠地冲击伤害|{param10:P}\/{param11:P}",
            "",
            "",
            "",
            "",
            "",
            ""
          ],
          "params": [
            0.60723,
            0.57096,
            0.35978,
            0.93366,
            0.5967,
            1.643,
            1.1554,
            0.51145,
            0.77314,
            1.54594,
            1.93097,
            0,
            0,
            0,
            0,
            0,
            0,
            0,
            0,
            0
          ]
        },
        "6": {
          "level": 6,
          "costItems": {
            "104330": 9,
            "112060": 9
          },
          "coinCost": 37500,
          "description": [
            "一段伤害|{param1:F1P}",
            "二段伤害|{param2:F1P}",
            "三段伤害|{param3:F1P}*2",
            "四段伤害|{param4:F1P}",
            "瞄准射击|{param5:F1P}",
            "一段蓄力瞄准射击|{param6:P}",
            "花筥箭伤害|{param7:F1P}",
            "藏蕴花矢伤害|{param8:F1P}",
            "下坠期间伤害|{param9:F1P}",
            "低空\/高空坠地冲击伤害|{param10:P}\/{param11:P}",
            "",
            "",
            "",
            "",
            "",
            ""
          ],
          "params": [
            0.64875,
            0.61,
            0.38438,
            0.9975,
            0.6375,
            1.736,
            1.2208,
            0.5404,
            0.826,
            1.65165,
            2.063,
            0,
            0,
            0,
            0,
            0,
            0,
            0,
            0,
            0
          ]
        },
        "7": {
          "level": 7,
          "costItems": {
            "104331": 4,
            "112061": 4,
            "113034": 1
          },
          "coinCost": 120000,
          "description": [
            "一段伤害|{param1:F1P}",
            "二段伤害|{param2:F1P}",
            "三段伤害|{param3:F1P}*2",
            "四段伤害|{param4:F1P}",
            "瞄准射击|{param5:F1P}",
            "一段蓄力瞄准射击|{param6:P}",
            "花筥箭伤害|{param7:F1P}",
            "藏蕴花矢伤害|{param8:F1P}",
            "下坠期间伤害|{param9:F1P}",
            "低空\/高空坠地冲击伤害|{param10:P}\/{param11:P}",
            "",
            "",
            "",
            "",
            "",
            ""
          ],
          "params": [
            0.70584,
            0.66368,
            0.4182,
            1.08528,
            0.6936,
            1.86,
            1.308,
            0.579,
            0.89869,
            1.797,
            2.24454,
            0,
            0,
            0,
            0,
            0,
            0,
            0,
            0,
            0
          ]
        },
        "8": {
          "level": 8,
          "costItems": {
            "104331": 6,
            "112061": 6,
            "113034": 1
          },
          "coinCost": 260000,
          "description": [
            "一段伤害|{param1:F1P}",
            "二段伤害|{param2:F1P}",
            "三段伤害|{param3:F1P}*2",
            "四段伤害|{param4:F1P}",
            "瞄准射击|{param5:F1P}",
            "一段蓄力瞄准射击|{param6:P}",
            "花筥箭伤害|{param7:F1P}",
            "藏蕴花矢伤害|{param8:F1P}",
            "下坠期间伤害|{param9:F1P}",
            "低空\/高空坠地冲击伤害|{param10:P}\/{param11:P}",
            "",
            "",
            "",
            "",
            "",
            ""
          ],
          "params": [
            0.76293,
            0.71736,
            0.45202,
            1.17306,
            0.7497,
            1.984,
            1.3952,
            0.6176,
            0.97138,
            1.94234,
            2.42609,
            0,
            0,
            0,
            0,
            0,
            0,
            0,
            0,
            0
          ]
        },
        "9": {
          "level": 9,
          "costItems": {
            "104331": 12,
            "112061": 9,
            "113034": 2
          },
          "coinCost": 450000,
          "description": [
            "一段伤害|{param1:F1P}",
            "二段伤害|{param2:F1P}",
            "三段伤害|{param3:F1P}*2",
            "四段伤害|{param4:F1P}",
            "瞄准射击|{param5:F1P}",
            "一段蓄力瞄准射击|{param6:P}",
            "花筥箭伤害|{param7:F1P}",
            "藏蕴花矢伤害|{param8:F1P}",
            "下坠期间伤害|{param9:F1P}",
            "低空\/高空坠地冲击伤害|{param10:P}\/{param11:P}",
            "",
            "",
            "",
            "",
            "",
            ""
          ],
          "params": [
            0.82002,
            0.77104,
            0.48585,
            1.26084,
            0.8058,
            2.108,
            1.4824,
            0.6562,
            1.04406,
            2.08769,
            2.60763,
            0,
            0,
            0,
            0,
            0,
            0,
            0,
            0,
            0
          ]
        },
        "10": {
          "level": 10,
          "costItems": {
            "104319": 1,
            "104331": 16,
            "112061": 12,
            "113034": 2
          },
          "coinCost": 700000,
          "description": [
            "一段伤害|{param1:F1P}",
            "二段伤害|{param2:F1P}",
            "三段伤害|{param3:F1P}*2",
            "四段伤害|{param4:F1P}",
            "瞄准射击|{param5:F1P}",
            "一段蓄力瞄准射击|{param6:P}",
            "花筥箭伤害|{param7:F1P}",
            "藏蕴花矢伤害|{param8:F1P}",
            "下坠期间伤害|{param9:F1P}",
            "低空\/高空坠地冲击伤害|{param10:P}\/{param11:P}",
            "",
            "",
            "",
            "",
            "",
            ""
          ],
          "params": [
            0.8823,
            0.8296,
            0.52275,
            1.3566,
            0.867,
            2.232,
            1.5696,
            0.6948,
            1.12336,
            2.24624,
            2.80568,
            0,
            0,
            0,
            0,
            0,
            0,
            0,
            0,
            0
          ]
        },
        "11": {
          "level": 11,
          "costItems": null,
          "coinCost": null,
          "description": [
            "一段伤害|{param1:F1P}",
            "二段伤害|{param2:F1P}",
            "三段伤害|{param3:F1P}*2",
            "四段伤害|{param4:F1P}",
            "瞄准射击|{param5:F1P}",
            "一段蓄力瞄准射击|{param6:P}",
            "花筥箭伤害|{param7:F1P}",
            "藏蕴花矢伤害|{param8:F1P}",
            "下坠期间伤害|{param9:F1P}",
            "低空\/高空坠地冲击伤害|{param10:P}\/{param11:P}",
            "",
            "",
            "",
            "",
            "",
            ""
          ],
          "params": [
            0.94458,
            0.88816,
            0.55965,
            1.45236,
            0.9282,
            2.356,
            1.6568,
            0.7334,
            1.20266,
            2.4048,
            3.00373,
            0,
            0,
            0,
            0,
            0,
            0,
            0,
            0,
            0
          ]
        },
        "12": {
          "level": 12,
          "costItems": null,
          "coinCost": null,
          "description": [
            "一段伤害|{param1:F1P}",
            "二段伤害|{param2:F1P}",
            "三段伤害|{param3:F1P}*2",
            "四段伤害|{param4:F1P}",
            "瞄准射击|{param5:F1P}",
            "一段蓄力瞄准射击|{param6:P}",
            "花筥箭伤害|{param7:F1P}",
            "藏蕴花矢伤害|{param8:F1P}",
            "下坠期间伤害|{param9:F1P}",
            "低空\/高空坠地冲击伤害|{param10:P}\/{param11:P}",
            "",
            "",
            "",
            "",
            "",
            ""
          ],
          "params": [
            1.00686,
            0.94672,
            0.59655,
            1.54812,
            0.9894,
            2.48,
            1.744,
            0.772,
            1.28195,
            2.56336,
            3.20178,
            0,
            0,
            0,
            0,
            0,
            0,
            0,
            0,
            0
          ]
        },
        "13": {
          "level": 13,
          "costItems": null,
          "coinCost": null,
          "description": [
            "一段伤害|{param1:F1P}",
            "二段伤害|{param2:F1P}",
            "三段伤害|{param3:F1P}*2",
            "四段伤害|{param4:F1P}",
            "瞄准射击|{param5:F1P}",
            "一段蓄力瞄准射击|{param6:P}",
            "花筥箭伤害|{param7:F1P}",
            "藏蕴花矢伤害|{param8:F1P}",
            "下坠期间伤害|{param9:F1P}",
            "低空\/高空坠地冲击伤害|{param10:P}\/{param11:P}",
            "",
            "",
            "",
            "",
            "",
            ""
          ],
          "params": [
            1.06914,
            1.00528,
            0.63345,
            1.64388,
            1.0506,
            2.635,
            1.853,
            0.82025,
            1.36125,
            2.72192,
            3.39982,
            0,
            0,
            0,
            0,
            0,
            0,
            0,
            0,
            0
          ]
        },
        "14": {
          "level": 14,
          "costItems": null,
          "coinCost": null,
          "description": [
            "一段伤害|{param1:F1P}",
            "二段伤害|{param2:F1P}",
            "三段伤害|{param3:F1P}*2",
            "四段伤害|{param4:F1P}",
            "瞄准射击|{param5:F1P}",
            "一段蓄力瞄准射击|{param6:P}",
            "花筥箭伤害|{param7:F1P}",
            "藏蕴花矢伤害|{param8:F1P}",
            "下坠期间伤害|{param9:F1P}",
            "低空\/高空坠地冲击伤害|{param10:P}\/{param11:P}",
            "",
            "",
            "",
            "",
            "",
            ""
          ],
          "params": [
            1.13142,
            1.06384,
            0.67035,
            1.73964,
            1.1118,
            2.79,
            1.962,
            0.8685,
            1.44054,
            2.88048,
            3.59787,
            0,
            0,
            0,
            0,
            0,
            0,
            0,
            0,
            0
          ]
        },
        "15": {
          "level": 15,
          "costItems": null,
          "coinCost": null,
          "description": [
            "一段伤害|{param1:F1P}",
            "二段伤害|{param2:F1P}",
            "三段伤害|{param3:F1P}*2",
            "四段伤害|{param4:F1P}",
            "瞄准射击|{param5:F1P}",
            "一段蓄力瞄准射击|{param6:P}",
            "花筥箭伤害|{param7:F1P}",
            "藏蕴花矢伤害|{param8:F1P}",
            "下坠期间伤害|{param9:F1P}",
            "低空\/高空坠地冲击伤害|{param10:P}\/{param11:P}",
            "",
            "",
            "",
            "",
            "",
            ""
          ],
          "params": [
            1.1937,
            1.1224,
            0.70725,
            1.8354,
            1.173,
            2.945,
            2.071,
            0.91675,
            1.51984,
            3.03904,
            3.79592,
            0,
            0,
            0,
            0,
            0,
            0,
            0,
            0,
            0
          ]
        }
      },
      "cooldown": 0,
      "cost": 0
    },
    "1": {
      "type": 0,
      "name": "识果种雷",
      "description": "提纳里向前投掷识种心雷，造成<color=#99FF88FF>草元素范围伤害<\/color>，并产生识蕴领域，神秘的幻象会持续嘲讽其中的敌人，吸引火力。\\n此外，提纳里将获得「通塞识」效果，使其花筥箭所需的蓄力时间减少2.4秒，该效果将在持续时间结束或提纳里发射3次花筥箭后消失。\\n\\n<i>「种子若在土壤之外枯萎死去，死去时仍是一粒。若它归壤于故土，就将结出千万粒来。」<\/i>",
      "icon": "Skill_S_Tighnari_01",
      "promote": {
        "1": {
          "level": 1,
          "costItems": null,
          "coinCost": null,
          "description": [
            "技能伤害|{param1:F1P}",
            "识蕴领域持续时间|{param2:F1}秒",
            "通塞识持续时间|{param3:F1}秒",
            "冷却时间|{param4:F1}秒",
            "",
            "",
            "",
            "",
            "",
            "",
            "",
            "",
            "",
            "",
            "",
            ""
          ],
          "params": [
            1.496,
            8,
            12,
            12,
            0,
            0,
            0,
            0,
            0,
            0,
            0,
            0,
            0,
            0,
            0,
            0,
            0,
            0,
            0,
            0
          ]
        },
        "2": {
          "level": 2,
          "costItems": {
            "104329": 3,
            "112059": 6
          },
          "coinCost": 12500,
          "description": [
            "技能伤害|{param1:F1P}",
            "识蕴领域持续时间|{param2:F1}秒",
            "通塞识持续时间|{param3:F1}秒",
            "冷却时间|{param4:F1}秒",
            "",
            "",
            "",
            "",
            "",
            "",
            "",
            "",
            "",
            "",
            "",
            ""
          ],
          "params": [
            1.6082,
            8,
            12,
            12,
            0,
            0,
            0,
            0,
            0,
            0,
            0,
            0,
            0,
            0,
            0,
            0,
            0,
            0,
            0,
            0
          ]
        },
        "3": {
          "level": 3,
          "costItems": {
            "104330": 2,
            "112060": 3
          },
          "coinCost": 17500,
          "description": [
            "技能伤害|{param1:F1P}",
            "识蕴领域持续时间|{param2:F1}秒",
            "通塞识持续时间|{param3:F1}秒",
            "冷却时间|{param4:F1}秒",
            "",
            "",
            "",
            "",
            "",
            "",
            "",
            "",
            "",
            "",
            "",
            ""
          ],
          "params": [
            1.7204,
            8,
            12,
            12,
            0,
            0,
            0,
            0,
            0,
            0,
            0,
            0,
            0,
            0,
            0,
            0,
            0,
            0,
            0,
            0
          ]
        },
        "4": {
          "level": 4,
          "costItems": {
            "104330": 4,
            "112060": 4
          },
          "coinCost": 25000,
          "description": [
            "技能伤害|{param1:F1P}",
            "识蕴领域持续时间|{param2:F1}秒",
            "通塞识持续时间|{param3:F1}秒",
            "冷却时间|{param4:F1}秒",
            "",
            "",
            "",
            "",
            "",
            "",
            "",
            "",
            "",
            "",
            "",
            ""
          ],
          "params": [
            1.87,
            8,
            12,
            12,
            0,
            0,
            0,
            0,
            0,
            0,
            0,
            0,
            0,
            0,
            0,
            0,
            0,
            0,
            0,
            0
          ]
        },
        "5": {
          "level": 5,
          "costItems": {
            "104330": 6,
            "112060": 6
          },
          "coinCost": 30000,
          "description": [
            "技能伤害|{param1:F1P}",
            "识蕴领域持续时间|{param2:F1}秒",
            "通塞识持续时间|{param3:F1}秒",
            "冷却时间|{param4:F1}秒",
            "",
            "",
            "",
            "",
            "",
            "",
            "",
            "",
            "",
            "",
            "",
            ""
          ],
          "params": [
            1.9822,
            8,
            12,
            12,
            0,
            0,
            0,
            0,
            0,
            0,
            0,
            0,
            0,
            0,
            0,
            0,
            0,
            0,
            0,
            0
          ]
        },
        "6": {
          "level": 6,
          "costItems": {
            "104330": 9,
            "112060": 9
          },
          "coinCost": 37500,
          "description": [
            "技能伤害|{param1:F1P}",
            "识蕴领域持续时间|{param2:F1}秒",
            "通塞识持续时间|{param3:F1}秒",
            "冷却时间|{param4:F1}秒",
            "",
            "",
            "",
            "",
            "",
            "",
            "",
            "",
            "",
            "",
            "",
            ""
          ],
          "params": [
            2.0944,
            8,
            12,
            12,
            0,
            0,
            0,
            0,
            0,
            0,
            0,
            0,
            0,
            0,
            0,
            0,
            0,
            0,
            0,
            0
          ]
        },
        "7": {
          "level": 7,
          "costItems": {
            "104331": 4,
            "112061": 4,
            "113034": 1
          },
          "coinCost": 120000,
          "description": [
            "技能伤害|{param1:F1P}",
            "识蕴领域持续时间|{param2:F1}秒",
            "通塞识持续时间|{param3:F1}秒",
            "冷却时间|{param4:F1}秒",
            "",
            "",
            "",
            "",
            "",
            "",
            "",
            "",
            "",
            "",
            "",
            ""
          ],
          "params": [
            2.244,
            8,
            12,
            12,
            0,
            0,
            0,
            0,
            0,
            0,
            0,
            0,
            0,
            0,
            0,
            0,
            0,
            0,
            0,
            0
          ]
        },
        "8": {
          "level": 8,
          "costItems": {
            "104331": 6,
            "112061": 6,
            "113034": 1
          },
          "coinCost": 260000,
          "description": [
            "技能伤害|{param1:F1P}",
            "识蕴领域持续时间|{param2:F1}秒",
            "通塞识持续时间|{param3:F1}秒",
            "冷却时间|{param4:F1}秒",
            "",
            "",
            "",
            "",
            "",
            "",
            "",
            "",
            "",
            "",
            "",
            ""
          ],
          "params": [
            2.3936,
            8,
            12,
            12,
            0,
            0,
            0,
            0,
            0,
            0,
            0,
            0,
            0,
            0,
            0,
            0,
            0,
            0,
            0,
            0
          ]
        },
        "9": {
          "level": 9,
          "costItems": {
            "104331": 12,
            "112061": 9,
            "113034": 2
          },
          "coinCost": 450000,
          "description": [
            "技能伤害|{param1:F1P}",
            "识蕴领域持续时间|{param2:F1}秒",
            "通塞识持续时间|{param3:F1}秒",
            "冷却时间|{param4:F1}秒",
            "",
            "",
            "",
            "",
            "",
            "",
            "",
            "",
            "",
            "",
            "",
            ""
          ],
          "params": [
            2.5432,
            8,
            12,
            12,
            0,
            0,
            0,
            0,
            0,
            0,
            0,
            0,
            0,
            0,
            0,
            0,
            0,
            0,
            0,
            0
          ]
        },
        "10": {
          "level": 10,
          "costItems": {
            "104319": 1,
            "104331": 16,
            "112061": 12,
            "113034": 2
          },
          "coinCost": 700000,
          "description": [
            "技能伤害|{param1:F1P}",
            "识蕴领域持续时间|{param2:F1}秒",
            "通塞识持续时间|{param3:F1}秒",
            "冷却时间|{param4:F1}秒",
            "",
            "",
            "",
            "",
            "",
            "",
            "",
            "",
            "",
            "",
            "",
            ""
          ],
          "params": [
            2.6928,
            8,
            12,
            12,
            0,
            0,
            0,
            0,
            0,
            0,
            0,
            0,
            0,
            0,
            0,
            0,
            0,
            0,
            0,
            0
          ]
        },
        "11": {
          "level": 11,
          "costItems": null,
          "coinCost": null,
          "description": [
            "技能伤害|{param1:F1P}",
            "识蕴领域持续时间|{param2:F1}秒",
            "通塞识持续时间|{param3:F1}秒",
            "冷却时间|{param4:F1}秒",
            "",
            "",
            "",
            "",
            "",
            "",
            "",
            "",
            "",
            "",
            "",
            ""
          ],
          "params": [
            2.8424,
            8,
            12,
            12,
            0,
            0,
            0,
            0,
            0,
            0,
            0,
            0,
            0,
            0,
            0,
            0,
            0,
            0,
            0,
            0
          ]
        },
        "12": {
          "level": 12,
          "costItems": null,
          "coinCost": null,
          "description": [
            "技能伤害|{param1:F1P}",
            "识蕴领域持续时间|{param2:F1}秒",
            "通塞识持续时间|{param3:F1}秒",
            "冷却时间|{param4:F1}秒",
            "",
            "",
            "",
            "",
            "",
            "",
            "",
            "",
            "",
            "",
            "",
            ""
          ],
          "params": [
            2.992,
            8,
            12,
            12,
            0,
            0,
            0,
            0,
            0,
            0,
            0,
            0,
            0,
            0,
            0,
            0,
            0,
            0,
            0,
            0
          ]
        },
        "13": {
          "level": 13,
          "costItems": null,
          "coinCost": null,
          "description": [
            "技能伤害|{param1:F1P}",
            "识蕴领域持续时间|{param2:F1}秒",
            "通塞识持续时间|{param3:F1}秒",
            "冷却时间|{param4:F1}秒",
            "",
            "",
            "",
            "",
            "",
            "",
            "",
            "",
            "",
            "",
            "",
            ""
          ],
          "params": [
            3.179,
            8,
            12,
            12,
            0,
            0,
            0,
            0,
            0,
            0,
            0,
            0,
            0,
            0,
            0,
            0,
            0,
            0,
            0,
            0
          ]
        },
        "14": {
          "level": 14,
          "costItems": null,
          "coinCost": null,
          "description": [
            "技能伤害|{param1:F1P}",
            "识蕴领域持续时间|{param2:F1}秒",
            "通塞识持续时间|{param3:F1}秒",
            "冷却时间|{param4:F1}秒",
            "",
            "",
            "",
            "",
            "",
            "",
            "",
            "",
            "",
            "",
            "",
            ""
          ],
          "params": [
            3.366,
            8,
            12,
            12,
            0,
            0,
            0,
            0,
            0,
            0,
            0,
            0,
            0,
            0,
            0,
            0,
            0,
            0,
            0,
            0
          ]
        },
        "15": {
          "level": 15,
          "costItems": null,
          "coinCost": null,
          "description": [
            "技能伤害|{param1:F1P}",
            "识蕴领域持续时间|{param2:F1}秒",
            "通塞识持续时间|{param3:F1}秒",
            "冷却时间|{param4:F1}秒",
            "",
            "",
            "",
            "",
            "",
            "",
            "",
            "",
            "",
            "",
            "",
            ""
          ],
          "params": [
            3.553,
            8,
            12,
            12,
            0,
            0,
            0,
            0,
            0,
            0,
            0,
            0,
            0,
            0,
            0,
            0,
            0,
            0,
            0,
            0
          ]
        }
      },
      "cooldown": 12,
      "cost": 0
    },
    "3": {
      "type": 1,
      "name": "造生缠藤箭",
      "description": "汇聚一切种子的力量，发射6枚能追踪敌人的缠藤箭，造成<color=#99FF88FF>草元素伤害<\/color>。\\n缠藤箭在命中后，将会产生次级缠藤箭，追踪附近的敌人，并在命中时造成<color=#99FF88FF>草元素伤害<\/color>。\\n\\n<i>「别想这么轻易摆脱，藤蔓之后再生藤蔓，如果不能彻底清理干净，后果可是很麻烦的。」<\/i>",
      "icon": "Skill_E_Tighnari_01",
      "promote": {
        "1": {
          "level": 1,
          "costItems": null,
          "coinCost": null,
          "description": [
            "缠藤箭伤害|{param1:F1P}",
            "次级缠藤箭伤害|{param2:F1P}",
            "冷却时间|{param3:F1}秒",
            "元素能量|{param4:I}",
            "",
            "",
            "",
            "",
            "",
            "",
            "",
            "",
            "",
            "",
            "",
            ""
          ],
          "params": [
            0.5562,
            0.6798,
            12,
            40,
            0,
            0,
            0,
            0,
            0,
            0,
            0,
            0,
            0,
            0,
            0,
            0,
            0,
            0,
            0,
            0
          ]
        },
        "2": {
          "level": 2,
          "costItems": {
            "104329": 3,
            "112059": 6
          },
          "coinCost": 12500,
          "description": [
            "缠藤箭伤害|{param1:F1P}",
            "次级缠藤箭伤害|{param2:F1P}",
            "冷却时间|{param3:F1}秒",
            "元素能量|{param4:I}",
            "",
            "",
            "",
            "",
            "",
            "",
            "",
            "",
            "",
            "",
            "",
            ""
          ],
          "params": [
            0.59791,
            0.73079,
            12,
            40,
            0,
            0,
            0,
            0,
            0,
            0,
            0,
            0,
            0,
            0,
            0,
            0,
            0,
            0,
            0,
            0
          ]
        },
        "3": {
          "level": 3,
          "costItems": {
            "104330": 2,
            "112060": 3
          },
          "coinCost": 17500,
          "description": [
            "缠藤箭伤害|{param1:F1P}",
            "次级缠藤箭伤害|{param2:F1P}",
            "冷却时间|{param3:F1}秒",
            "元素能量|{param4:I}",
            "",
            "",
            "",
            "",
            "",
            "",
            "",
            "",
            "",
            "",
            "",
            ""
          ],
          "params": [
            0.63963,
            0.78177,
            12,
            40,
            0,
            0,
            0,
            0,
            0,
            0,
            0,
            0,
            0,
            0,
            0,
            0,
            0,
            0,
            0,
            0
          ]
        },
        "4": {
          "level": 4,
          "costItems": {
            "104330": 4,
            "112060": 4
          },
          "coinCost": 25000,
          "description": [
            "缠藤箭伤害|{param1:F1P}",
            "次级缠藤箭伤害|{param2:F1P}",
            "冷却时间|{param3:F1}秒",
            "元素能量|{param4:I}",
            "",
            "",
            "",
            "",
            "",
            "",
            "",
            "",
            "",
            "",
            "",
            ""
          ],
          "params": [
            0.69525,
            0.84975,
            12,
            40,
            0,
            0,
            0,
            0,
            0,
            0,
            0,
            0,
            0,
            0,
            0,
            0,
            0,
            0,
            0,
            0
          ]
        },
        "5": {
          "level": 5,
          "costItems": {
            "104330": 6,
            "112060": 6
          },
          "coinCost": 30000,
          "description": [
            "缠藤箭伤害|{param1:F1P}",
            "次级缠藤箭伤害|{param2:F1P}",
            "冷却时间|{param3:F1}秒",
            "元素能量|{param4:I}",
            "",
            "",
            "",
            "",
            "",
            "",
            "",
            "",
            "",
            "",
            "",
            ""
          ],
          "params": [
            0.73697,
            0.90074,
            12,
            40,
            0,
            0,
            0,
            0,
            0,
            0,
            0,
            0,
            0,
            0,
            0,
            0,
            0,
            0,
            0,
            0
          ]
        },
        "6": {
          "level": 6,
          "costItems": {
            "104330": 9,
            "112060": 9
          },
          "coinCost": 37500,
          "description": [
            "缠藤箭伤害|{param1:F1P}",
            "次级缠藤箭伤害|{param2:F1P}",
            "冷却时间|{param3:F1}秒",
            "元素能量|{param4:I}",
            "",
            "",
            "",
            "",
            "",
            "",
            "",
            "",
            "",
            "",
            "",
            ""
          ],
          "params": [
            0.77868,
            0.95172,
            12,
            40,
            0,
            0,
            0,
            0,
            0,
            0,
            0,
            0,
            0,
            0,
            0,
            0,
            0,
            0,
            0,
            0
          ]
        },
        "7": {
          "level": 7,
          "costItems": {
            "104331": 4,
            "112061": 4,
            "113034": 1
          },
          "coinCost": 120000,
          "description": [
            "缠藤箭伤害|{param1:F1P}",
            "次级缠藤箭伤害|{param2:F1P}",
            "冷却时间|{param3:F1}秒",
            "元素能量|{param4:I}",
            "",
            "",
            "",
            "",
            "",
            "",
            "",
            "",
            "",
            "",
            "",
            ""
          ],
          "params": [
            0.8343,
            1.0197,
            12,
            40,
            0,
            0,
            0,
            0,
            0,
            0,
            0,
            0,
            0,
            0,
            0,
            0,
            0,
            0,
            0,
            0
          ]
        },
        "8": {
          "level": 8,
          "costItems": {
            "104331": 6,
            "112061": 6,
            "113034": 1
          },
          "coinCost": 260000,
          "description": [
            "缠藤箭伤害|{param1:F1P}",
            "次级缠藤箭伤害|{param2:F1P}",
            "冷却时间|{param3:F1}秒",
            "元素能量|{param4:I}",
            "",
            "",
            "",
            "",
            "",
            "",
            "",
            "",
            "",
            "",
            "",
            ""
          ],
          "params": [
            0.88992,
            1.08768,
            12,
            40,
            0,
            0,
            0,
            0,
            0,
            0,
            0,
            0,
            0,
            0,
            0,
            0,
            0,
            0,
            0,
            0
          ]
        },
        "9": {
          "level": 9,
          "costItems": {
            "104331": 12,
            "112061": 9,
            "113034": 2
          },
          "coinCost": 450000,
          "description": [
            "缠藤箭伤害|{param1:F1P}",
            "次级缠藤箭伤害|{param2:F1P}",
            "冷却时间|{param3:F1}秒",
            "元素能量|{param4:I}",
            "",
            "",
            "",
            "",
            "",
            "",
            "",
            "",
            "",
            "",
            "",
            ""
          ],
          "params": [
            0.94554,
            1.15566,
            12,
            40,
            0,
            0,
            0,
            0,
            0,
            0,
            0,
            0,
            0,
            0,
            0,
            0,
            0,
            0,
            0,
            0
          ]
        },
        "10": {
          "level": 10,
          "costItems": {
            "104319": 1,
            "104331": 16,
            "112061": 12,
            "113034": 2
          },
          "coinCost": 700000,
          "description": [
            "缠藤箭伤害|{param1:F1P}",
            "次级缠藤箭伤害|{param2:F1P}",
            "冷却时间|{param3:F1}秒",
            "元素能量|{param4:I}",
            "",
            "",
            "",
            "",
            "",
            "",
            "",
            "",
            "",
            "",
            "",
            ""
          ],
          "params": [
            1.00116,
            1.22364,
            12,
            40,
            0,
            0,
            0,
            0,
            0,
            0,
            0,
            0,
            0,
            0,
            0,
            0,
            0,
            0,
            0,
            0
          ]
        },
        "11": {
          "level": 11,
          "costItems": null,
          "coinCost": null,
          "description": [
            "缠藤箭伤害|{param1:F1P}",
            "次级缠藤箭伤害|{param2:F1P}",
            "冷却时间|{param3:F1}秒",
            "元素能量|{param4:I}",
            "",
            "",
            "",
            "",
            "",
            "",
            "",
            "",
            "",
            "",
            "",
            ""
          ],
          "params": [
            1.05678,
            1.29162,
            12,
            40,
            0,
            0,
            0,
            0,
            0,
            0,
            0,
            0,
            0,
            0,
            0,
            0,
            0,
            0,
            0,
            0
          ]
        },
        "12": {
          "level": 12,
          "costItems": null,
          "coinCost": null,
          "description": [
            "缠藤箭伤害|{param1:F1P}",
            "次级缠藤箭伤害|{param2:F1P}",
            "冷却时间|{param3:F1}秒",
            "元素能量|{param4:I}",
            "",
            "",
            "",
            "",
            "",
            "",
            "",
            "",
            "",
            "",
            "",
            ""
          ],
          "params": [
            1.1124,
            1.3596,
            12,
            40,
            0,
            0,
            0,
            0,
            0,
            0,
            0,
            0,
            0,
            0,
            0,
            0,
            0,
            0,
            0,
            0
          ]
        },
        "13": {
          "level": 13,
          "costItems": null,
          "coinCost": null,
          "description": [
            "缠藤箭伤害|{param1:F1P}",
            "次级缠藤箭伤害|{param2:F1P}",
            "冷却时间|{param3:F1}秒",
            "元素能量|{param4:I}",
            "",
            "",
            "",
            "",
            "",
            "",
            "",
            "",
            "",
            "",
            "",
            ""
          ],
          "params": [
            1.18193,
            1.44457,
            12,
            40,
            0,
            0,
            0,
            0,
            0,
            0,
            0,
            0,
            0,
            0,
            0,
            0,
            0,
            0,
            0,
            0
          ]
        },
        "14": {
          "level": 14,
          "costItems": null,
          "coinCost": null,
          "description": [
            "缠藤箭伤害|{param1:F1P}",
            "次级缠藤箭伤害|{param2:F1P}",
            "冷却时间|{param3:F1}秒",
            "元素能量|{param4:I}",
            "",
            "",
            "",
            "",
            "",
            "",
            "",
            "",
            "",
            "",
            "",
            ""
          ],
          "params": [
            1.25145,
            1.52955,
            12,
            40,
            0,
            0,
            0,
            0,
            0,
            0,
            0,
            0,
            0,
            0,
            0,
            0,
            0,
            0,
            0,
            0
          ]
        },
        "15": {
          "level": 15,
          "costItems": null,
          "coinCost": null,
          "description": [
            "缠藤箭伤害|{param1:F1P}",
            "次级缠藤箭伤害|{param2:F1P}",
            "冷却时间|{param3:F1}秒",
            "元素能量|{param4:I}",
            "",
            "",
            "",
            "",
            "",
            "",
            "",
            "",
            "",
            "",
            "",
            ""
          ],
          "params": [
            1.32097,
            1.61452,
            12,
            40,
            0,
            0,
            0,
            0,
            0,
            0,
            0,
            0,
            0,
            0,
            0,
            0,
            0,
            0,
            0,
            0
          ]
        }
      },
      "cooldown": 12,
      "cost": 40
    },
    "4": {
      "type": 2,
      "name": "眼识殊明",
      "description": "提纳里发射<color=#FFD780FF>花筥箭<\/color>后，元素精通提升50点，持续4秒。",
      "icon": "UI_Talent_S_Tighnari_05"
    },
    "5": {
      "type": 2,
      "name": "诸叶辨通",
      "description": "提纳里的每点元素精通，都会使其重击与<color=#FFD780FF>造生缠藤箭<\/color>造成的伤害提升0.06%。\\n通过这种方式，至多使上述攻击造成的伤害提升60%。",
      "icon": "UI_Talent_S_Tighnari_06"
    },
    "6": {
      "type": 2,
      "name": "闳览博物",
      "description": "在小地图上显示周围的<color=#FFD780FF>须弥区域特产<\/color>的位置。",
      "icon": "UI_Talent_S_Tighnari_07"
    }
  },
  "constellation": {
    "0": {
      "name": "由根须断定肇始",
      "description": "提纳里重击的暴击率提高15%。",
      "icon": "UI_Talent_S_Tighnari_01"
    },
    "1": {
      "name": "由茎干剖析来缘",
      "description": "当<color=#FFD780FF>识果种雷<\/color>的识蕴领域中存在敌人时，提纳里获得20%<color=#99FF88FF>草元素伤害加成<\/color>。\\n识蕴领域持续时间结束或其中不存在敌人后，该效果至多持续6秒。",
      "icon": "UI_Talent_S_Tighnari_02"
    },
    "2": {
      "name": "由枝节知晓造化",
      "description": "<color=#FFD780FF>造生缠藤箭<\/color>的技能等级提高3级。\\n至多提升至15级。",
      "icon": "UI_Talent_U_Tighnari_01"
    },
    "3": {
      "name": "由片叶管窥枯荣",
      "description": "施放<color=#FFD780FF>造生缠藤箭<\/color>时，队伍中附近的所有角色的元素精通提升60点，持续8秒。若造生缠藤箭触发了燃烧、绽放、原激化或蔓激化反应，元素精通将进一步提升60点，并刷新该状态的持续时间。",
      "icon": "UI_Talent_S_Tighnari_03"
    },
    "4": {
      "name": "由繁花明了悟觉",
      "description": "<color=#FFD780FF>识果种雷<\/color>的技能等级提高3级。\\n至多提升至15级。",
      "icon": "UI_Talent_U_Tighnari_02"
    },
    "5": {
      "name": "由硕实品论应果",
      "description": "<color=#FFD780FF>花筥箭<\/color>所需的蓄力时间减少0.9秒，并在命中后能产生1枚额外的藏蕴花矢，能造成提纳里攻击力150%的伤害。",
      "icon": "UI_Talent_S_Tighnari_04"
    }
  }
}