{
  "id": 10000086,
  "rank": 5,
  "name": "莱欧斯利",
  "element": "Ice",
  "weaponType": "WEAPON_CATALYST",
  "icon": "UI_AvatarIcon_Wriothesley",
  "birthday": [
    11,
    23
  ],
  "release": 1697554800,
  "route": "Wriothesley",
  "fetter": {
    "title": "寂罪的密使",
    "detail": "梅洛彼得堡的公爵，隐于漆黑海底的领主。",
    "constellation": "守狱犬座",
    "native": "梅洛彼得堡",
    "cv": {
      "EN": "乔·齐贾",
      "CHS": "刘北辰",
      "JP": "小野大辅",
      "KR": "权昌旭"
    }
  },
  "upgrade": {
    "prop": [
      {
        "propType": "FIGHT_PROP_BASE_HP",
        "initValue": 1058.18518,
        "type": "GROW_CURVE_HP_S5"
      },
      {
        "propType": "FIGHT_PROP_BASE_ATTACK",
        "initValue": 24.206,
        "type": "GROW_CURVE_ATTACK_S5"
      },
      {
        "propType": "FIGHT_PROP_BASE_DEFENSE",
        "initValue": 59.41119,
        "type": "GROW_CURVE_HP_S5"
      }
    ],
    "promote": [
      {
        "unlockMaxLevel": 20,
        "promoteLevel": 0
      },
      {
        "promoteLevel": 1,
        "costItems": {
          "101239": 3,
          "104161": 1,
          "112083": 3
        },
        "unlockMaxLevel": 40,
        "addProps": {
          "FIGHT_PROP_BASE_HP": 907.29816,
          "FIGHT_PROP_BASE_DEFENSE": 50.9409,
          "FIGHT_PROP_BASE_ATTACK": 20.75294,
          "FIGHT_PROP_CRITICAL_HURT": 0
        },
        "requiredPlayerLevel": 15,
        "coinCost": 20000
      },
      {
        "promoteLevel": 2,
        "costItems": {
          "101239": 10,
          "104162": 3,
          "112083": 15,
          "113052": 2
        },
        "unlockMaxLevel": 50,
        "addProps": {
          "FIGHT_PROP_BASE_HP": 1551.95728,
          "FIGHT_PROP_BASE_DEFENSE": 87.13575,
          "FIGHT_PROP_BASE_ATTACK": 35.49845,
          "FIGHT_PROP_CRITICAL_HURT": 0.096
        },
        "requiredPlayerLevel": 25,
        "coinCost": 40000
      },
      {
        "promoteLevel": 3,
        "costItems": {
          "101239": 20,
          "104162": 6,
          "112084": 12,
          "113052": 4
        },
        "unlockMaxLevel": 60,
        "addProps": {
          "FIGHT_PROP_BASE_HP": 2411.50293,
          "FIGHT_PROP_BASE_DEFENSE": 135.39555,
          "FIGHT_PROP_BASE_ATTACK": 55.15913,
          "FIGHT_PROP_CRITICAL_HURT": 0.192
        },
        "requiredPlayerLevel": 30,
        "coinCost": 60000
      },
      {
        "promoteLevel": 4,
        "costItems": {
          "101239": 30,
          "104163": 3,
          "112084": 18,
          "113052": 8
        },
        "unlockMaxLevel": 70,
        "addProps": {
          "FIGHT_PROP_BASE_HP": 3056.16211,
          "FIGHT_PROP_BASE_DEFENSE": 171.59039,
          "FIGHT_PROP_BASE_ATTACK": 69.90464,
          "FIGHT_PROP_CRITICAL_HURT": 0.192
        },
        "requiredPlayerLevel": 35,
        "coinCost": 80000
      },
      {
        "promoteLevel": 5,
        "costItems": {
          "101239": 45,
          "104163": 6,
          "112085": 12,
          "113052": 12
        },
        "unlockMaxLevel": 80,
        "addProps": {
          "FIGHT_PROP_BASE_HP": 3700.82129,
          "FIGHT_PROP_BASE_DEFENSE": 207.78525,
          "FIGHT_PROP_BASE_ATTACK": 84.65015,
          "FIGHT_PROP_CRITICAL_HURT": 0.288
        },
        "requiredPlayerLevel": 40,
        "coinCost": 100000
      },
      {
        "promoteLevel": 6,
        "costItems": {
          "101239": 60,
          "104164": 6,
          "112085": 24,
          "113052": 20
        },
        "unlockMaxLevel": 90,
        "addProps": {
          "FIGHT_PROP_BASE_HP": 4345.48047,
          "FIGHT_PROP_BASE_DEFENSE": 243.9801,
          "FIGHT_PROP_BASE_ATTACK": 99.39566,
          "FIGHT_PROP_CRITICAL_HURT": 0.384
        },
        "requiredPlayerLevel": 50,
        "coinCost": 120000
      }
    ]
  },
  "other": {
    "costume": [
      {
        "name": "凛冬夜啸",
        "description": "莱欧斯利的装扮款式。彰显威严与力量感的衣装，粗犷的灰狼驳头链是他统领梅洛彼得堡的标志。",
        "isDefault": true
      }
    ],
    "furnitureId": 368172,
    "nameCard": {
      "id": 210175,
      "name": "莱欧斯利·缄锁",
      "description": "名片纹饰。\\n维持梅洛彼得堡内部的平衡并不是简单的工作，为此，他需要一些灵活的手腕，适量严苛，和少许令人叹息的残酷。",
      "icon": "UI_NameCardIcon_Wriothesley"
    },
    "specialFood": {
      "id": 108604,
      "name": "秘烤肋排",
      "rank": 2,
      "effectIcon": "UI_Buff_Item_Recovery_HpAdd",
      "icon": "UI_ItemIcon_108604"
    }
  },
  "ascension": {
    "101239": 1,
    "104161": 2,
    "104162": 3,
    "104163": 4,
    "104164": 5,
    "104319": 5,
    "104344": 2,
    "104345": 3,
    "104346": 4,
    "112083": 1,
    "112084": 2,
    "112085": 3,
    "113047": 5,
    "113052": 4
  },
  "talent": {
    "0": {
      "type": 0,
      "name": "普通攻击·迅烈倾霜拳",
      "description": "<color=#FFD780FF>普通攻击<\/color>\\n将坚冰凝聚于拳锋，挥出迅猛的<color=#FFD780FF>斥逐拳<\/color>，进行至多五段的快速打击，造成<color=#99FFFFFF>冰元素伤害<\/color>。\\n此外，施放元素战技「冰牙突驰」或进行冲刺后的一小段时间内，普通攻击连击段数不会重置。\\n\\n<color=#FFD780FF>重击<\/color>\\n消耗一定体力，腾跃而起，打出<color=#FFD780FF>凌跃拳<\/color>，造成<color=#99FFFFFF>冰元素范围伤害<\/color>。\\n\\n<color=#FFD780FF>下落攻击<\/color>\\n从空中下坠冲击地面，攻击下落路径上的敌人，并在落地时造成<color=#99FFFFFF>冰元素范围伤害<\/color>。",
      "icon": "Skill_A_Catalyst_MD",
      "promote": {
        "1": {
          "level": 1,
          "costItems": null,
          "coinCost": null,
          "description": [
            "一段伤害|{param1:F1P}",
            "二段伤害|{param2:F1P}",
            "三段伤害|{param3:F1P}",
            "四段伤害|{param4:F1P}+{param5:F1P}",
            "五段伤害|{param6:F1P}",
            "重击伤害|{param7:F1P}",
            "重击体力消耗|{param8:F1}点",
            "下坠期间伤害|{param9:F1P}",
            "低空\/高空坠地冲击伤害|{param10:P}\/{param11:P}",
            "",
            "",
            "",
            "",
            "",
            "",
            ""
          ],
          "params": [
            0.5336,
            0.51799,
            0.67223,
            0.37904,
            0.37904,
            0.90742,
            1.5296,
            50,
            0.56829,
            1.13634,
            1.41934,
            0,
            0,
            0,
            0,
            0,
            0,
            0,
            0,
            0
          ]
        },
        "2": {
          "level": 2,
          "costItems": {
            "104344": 3,
            "112083": 6
          },
          "coinCost": 12500,
          "description": [
            "一段伤害|{param1:F1P}",
            "二段伤害|{param2:F1P}",
            "三段伤害|{param3:F1P}",
            "四段伤害|{param4:F1P}+{param5:F1P}",
            "五段伤害|{param6:F1P}",
            "重击伤害|{param7:F1P}",
            "重击体力消耗|{param8:F1}点",
            "下坠期间伤害|{param9:F1P}",
            "低空\/高空坠地冲击伤害|{param10:P}\/{param11:P}",
            "",
            "",
            "",
            "",
            "",
            "",
            ""
          ],
          "params": [
            0.57703,
            0.56015,
            0.72694,
            0.40989,
            0.40989,
            0.98128,
            1.64432,
            50,
            0.61454,
            1.22883,
            1.53487,
            0,
            0,
            0,
            0,
            0,
            0,
            0,
            0,
            0
          ]
        },
        "3": {
          "level": 3,
          "costItems": {
            "104345": 2,
            "112084": 3
          },
          "coinCost": 17500,
          "description": [
            "一段伤害|{param1:F1P}",
            "二段伤害|{param2:F1P}",
            "三段伤害|{param3:F1P}",
            "四段伤害|{param4:F1P}+{param5:F1P}",
            "五段伤害|{param6:F1P}",
            "重击伤害|{param7:F1P}",
            "重击体力消耗|{param8:F1}点",
            "下坠期间伤害|{param9:F1P}",
            "低空\/高空坠地冲击伤害|{param10:P}\/{param11:P}",
            "",
            "",
            "",
            "",
            "",
            "",
            ""
          ],
          "params": [
            0.62046,
            0.60231,
            0.78166,
            0.44074,
            0.44074,
            1.05514,
            1.75904,
            50,
            0.6608,
            1.32132,
            1.6504,
            0,
            0,
            0,
            0,
            0,
            0,
            0,
            0,
            0
          ]
        },
        "4": {
          "level": 4,
          "costItems": {
            "104345": 4,
            "112084": 4
          },
          "coinCost": 25000,
          "description": [
            "一段伤害|{param1:F1P}",
            "二段伤害|{param2:F1P}",
            "三段伤害|{param3:F1P}",
            "四段伤害|{param4:F1P}+{param5:F1P}",
            "五段伤害|{param6:F1P}",
            "重击伤害|{param7:F1P}",
            "重击体力消耗|{param8:F1}点",
            "下坠期间伤害|{param9:F1P}",
            "低空\/高空坠地冲击伤害|{param10:P}\/{param11:P}",
            "",
            "",
            "",
            "",
            "",
            "",
            ""
          ],
          "params": [
            0.68251,
            0.66254,
            0.85983,
            0.48482,
            0.48482,
            1.16065,
            1.912,
            50,
            0.72688,
            1.45345,
            1.81544,
            0,
            0,
            0,
            0,
            0,
            0,
            0,
            0,
            0
          ]
        },
        "5": {
          "level": 5,
          "costItems": {
            "104345": 6,
            "112084": 6
          },
          "coinCost": 30000,
          "description": [
            "一段伤害|{param1:F1P}",
            "二段伤害|{param2:F1P}",
            "三段伤害|{param3:F1P}",
            "四段伤害|{param4:F1P}+{param5:F1P}",
            "五段伤害|{param6:F1P}",
            "重击伤害|{param7:F1P}",
            "重击体力消耗|{param8:F1}点",
            "下坠期间伤害|{param9:F1P}",
            "低空\/高空坠地冲击伤害|{param10:P}\/{param11:P}",
            "",
            "",
            "",
            "",
            "",
            "",
            ""
          ],
          "params": [
            0.72594,
            0.7047,
            0.91454,
            0.51567,
            0.51567,
            1.23451,
            2.02672,
            50,
            0.77314,
            1.54594,
            1.93097,
            0,
            0,
            0,
            0,
            0,
            0,
            0,
            0,
            0
          ]
        },
        "6": {
          "level": 6,
          "costItems": {
            "104345": 9,
            "112084": 9
          },
          "coinCost": 37500,
          "description": [
            "一段伤害|{param1:F1P}",
            "二段伤害|{param2:F1P}",
            "三段伤害|{param3:F1P}",
            "四段伤害|{param4:F1P}+{param5:F1P}",
            "五段伤害|{param6:F1P}",
            "重击伤害|{param7:F1P}",
            "重击体力消耗|{param8:F1}点",
            "下坠期间伤害|{param9:F1P}",
            "低空\/高空坠地冲击伤害|{param10:P}\/{param11:P}",
            "",
            "",
            "",
            "",
            "",
            "",
            ""
          ],
          "params": [
            0.77557,
            0.75289,
            0.97707,
            0.55093,
            0.55093,
            1.31893,
            2.14144,
            50,
            0.826,
            1.65165,
            2.063,
            0,
            0,
            0,
            0,
            0,
            0,
            0,
            0,
            0
          ]
        },
        "7": {
          "level": 7,
          "costItems": {
            "104346": 4,
            "112085": 4,
            "113047": 1
          },
          "coinCost": 120000,
          "description": [
            "一段伤害|{param1:F1P}",
            "二段伤害|{param2:F1P}",
            "三段伤害|{param3:F1P}",
            "四段伤害|{param4:F1P}+{param5:F1P}",
            "五段伤害|{param6:F1P}",
            "重击伤害|{param7:F1P}",
            "重击体力消耗|{param8:F1}点",
            "下坠期间伤害|{param9:F1P}",
            "低空\/高空坠地冲击伤害|{param10:P}\/{param11:P}",
            "",
            "",
            "",
            "",
            "",
            "",
            ""
          ],
          "params": [
            0.84383,
            0.81914,
            1.06306,
            0.59941,
            0.59941,
            1.43499,
            2.2944,
            50,
            0.89869,
            1.797,
            2.24454,
            0,
            0,
            0,
            0,
            0,
            0,
            0,
            0,
            0
          ]
        },
        "8": {
          "level": 8,
          "costItems": {
            "104346": 6,
            "112085": 6,
            "113047": 1
          },
          "coinCost": 260000,
          "description": [
            "一段伤害|{param1:F1P}",
            "二段伤害|{param2:F1P}",
            "三段伤害|{param3:F1P}",
            "四段伤害|{param4:F1P}+{param5:F1P}",
            "五段伤害|{param6:F1P}",
            "重击伤害|{param7:F1P}",
            "重击体力消耗|{param8:F1}点",
            "下坠期间伤害|{param9:F1P}",
            "低空\/高空坠地冲击伤害|{param10:P}\/{param11:P}",
            "",
            "",
            "",
            "",
            "",
            "",
            ""
          ],
          "params": [
            0.91208,
            0.8854,
            1.14904,
            0.64789,
            0.64789,
            1.55106,
            2.44736,
            50,
            0.97138,
            1.94234,
            2.42609,
            0,
            0,
            0,
            0,
            0,
            0,
            0,
            0,
            0
          ]
        },
        "9": {
          "level": 9,
          "costItems": {
            "104346": 12,
            "112085": 9,
            "113047": 2
          },
          "coinCost": 450000,
          "description": [
            "一段伤害|{param1:F1P}",
            "二段伤害|{param2:F1P}",
            "三段伤害|{param3:F1P}",
            "四段伤害|{param4:F1P}+{param5:F1P}",
            "五段伤害|{param6:F1P}",
            "重击伤害|{param7:F1P}",
            "重击体力消耗|{param8:F1}点",
            "下坠期间伤害|{param9:F1P}",
            "低空\/高空坠地冲击伤害|{param10:P}\/{param11:P}",
            "",
            "",
            "",
            "",
            "",
            "",
            ""
          ],
          "params": [
            0.98033,
            0.95165,
            1.23502,
            0.69638,
            0.69638,
            1.66712,
            2.60032,
            50,
            1.04406,
            2.08769,
            2.60763,
            0,
            0,
            0,
            0,
            0,
            0,
            0,
            0,
            0
          ]
        },
        "10": {
          "level": 10,
          "costItems": {
            "104319": 1,
            "104346": 16,
            "112085": 12,
            "113047": 2
          },
          "coinCost": 700000,
          "description": [
            "一段伤害|{param1:F1P}",
            "二段伤害|{param2:F1P}",
            "三段伤害|{param3:F1P}",
            "四段伤害|{param4:F1P}+{param5:F1P}",
            "五段伤害|{param6:F1P}",
            "重击伤害|{param7:F1P}",
            "重击体力消耗|{param8:F1}点",
            "下坠期间伤害|{param9:F1P}",
            "低空\/高空坠地冲击伤害|{param10:P}\/{param11:P}",
            "",
            "",
            "",
            "",
            "",
            "",
            ""
          ],
          "params": [
            1.05478,
            1.02393,
            1.32882,
            0.74927,
            0.74927,
            1.79374,
            2.75328,
            50,
            1.12336,
            2.24624,
            2.80568,
            0,
            0,
            0,
            0,
            0,
            0,
            0,
            0,
            0
          ]
        },
        "11": {
          "level": 11,
          "costItems": null,
          "coinCost": null,
          "description": [
            "一段伤害|{param1:F1P}",
            "二段伤害|{param2:F1P}",
            "三段伤害|{param3:F1P}",
            "四段伤害|{param4:F1P}+{param5:F1P}",
            "五段伤害|{param6:F1P}",
            "重击伤害|{param7:F1P}",
            "重击体力消耗|{param8:F1}点",
            "下坠期间伤害|{param9:F1P}",
            "低空\/高空坠地冲击伤害|{param10:P}\/{param11:P}",
            "",
            "",
            "",
            "",
            "",
            "",
            ""
          ],
          "params": [
            1.12924,
            1.0962,
            1.42262,
            0.80216,
            0.80216,
            1.92035,
            2.90624,
            50,
            1.20266,
            2.4048,
            3.00373,
            0,
            0,
            0,
            0,
            0,
            0,
            0,
            0,
            0
          ]
        },
        "12": {
          "level": 12,
          "costItems": null,
          "coinCost": null,
          "description": [
            "一段伤害|{param1:F1P}",
            "二段伤害|{param2:F1P}",
            "三段伤害|{param3:F1P}",
            "四段伤害|{param4:F1P}+{param5:F1P}",
            "五段伤害|{param6:F1P}",
            "重击伤害|{param7:F1P}",
            "重击体力消耗|{param8:F1}点",
            "下坠期间伤害|{param9:F1P}",
            "低空\/高空坠地冲击伤害|{param10:P}\/{param11:P}",
            "",
            "",
            "",
            "",
            "",
            "",
            ""
          ],
          "params": [
            1.20369,
            1.16848,
            1.51642,
            0.85505,
            0.85505,
            2.04697,
            3.0592,
            50,
            1.28195,
            2.56336,
            3.20178,
            0,
            0,
            0,
            0,
            0,
            0,
            0,
            0,
            0
          ]
        },
        "13": {
          "level": 13,
          "costItems": null,
          "coinCost": null,
          "description": [
            "一段伤害|{param1:F1P}",
            "二段伤害|{param2:F1P}",
            "三段伤害|{param3:F1P}",
            "四段伤害|{param4:F1P}+{param5:F1P}",
            "五段伤害|{param6:F1P}",
            "重击伤害|{param7:F1P}",
            "重击体力消耗|{param8:F1}点",
            "下坠期间伤害|{param9:F1P}",
            "低空\/高空坠地冲击伤害|{param10:P}\/{param11:P}",
            "",
            "",
            "",
            "",
            "",
            "",
            ""
          ],
          "params": [
            1.27815,
            1.24076,
            1.61022,
            0.90794,
            0.90794,
            2.17359,
            3.2504,
            50,
            1.36125,
            2.72192,
            3.39982,
            0,
            0,
            0,
            0,
            0,
            0,
            0,
            0,
            0
          ]
        },
        "14": {
          "level": 14,
          "costItems": null,
          "coinCost": null,
          "description": [
            "一段伤害|{param1:F1P}",
            "二段伤害|{param2:F1P}",
            "三段伤害|{param3:F1P}",
            "四段伤害|{param4:F1P}+{param5:F1P}",
            "五段伤害|{param6:F1P}",
            "重击伤害|{param7:F1P}",
            "重击体力消耗|{param8:F1}点",
            "下坠期间伤害|{param9:F1P}",
            "低空\/高空坠地冲击伤害|{param10:P}\/{param11:P}",
            "",
            "",
            "",
            "",
            "",
            "",
            ""
          ],
          "params": [
            1.3526,
            1.31304,
            1.70402,
            0.96082,
            0.96082,
            2.3002,
            3.4416,
            50,
            1.44054,
            2.88048,
            3.59787,
            0,
            0,
            0,
            0,
            0,
            0,
            0,
            0,
            0
          ]
        },
        "15": {
          "level": 15,
          "costItems": null,
          "coinCost": null,
          "description": [
            "一段伤害|{param1:F1P}",
            "二段伤害|{param2:F1P}",
            "三段伤害|{param3:F1P}",
            "四段伤害|{param4:F1P}+{param5:F1P}",
            "五段伤害|{param6:F1P}",
            "重击伤害|{param7:F1P}",
            "重击体力消耗|{param8:F1}点",
            "下坠期间伤害|{param9:F1P}",
            "低空\/高空坠地冲击伤害|{param10:P}\/{param11:P}",
            "",
            "",
            "",
            "",
            "",
            "",
            ""
          ],
          "params": [
            1.42706,
            1.38531,
            1.79782,
            1.01371,
            1.01371,
            2.42682,
            3.6328,
            50,
            1.51984,
            3.03904,
            3.79592,
            0,
            0,
            0,
            0,
            0,
            0,
            0,
            0,
            0
          ]
        }
      },
      "cooldown": 0,
      "cost": 0
    },
    "1": {
      "type": 0,
      "name": "冰牙突驰",
      "description": "迅速调整呼吸、节奏与步伐，向前短距离冲刺，进入<color=#FFD780FF>寒烈的惩裁<\/color>状态，以发起更为猛烈的进攻。\\n\\n<color=#FFD780FF>寒烈的惩裁<\/color>\\n·提高莱欧斯利的抗打断能力；\\n·生命值高于50%时，强化<color=#FFD780FF>「普通攻击·迅烈倾霜拳」<\/color>的斥逐拳，使其造成的伤害提升；命中时莱欧斯利将损失一定的生命值，每0.1秒至多因此损失一次生命值；\\n效果将在莱欧斯利退场时解除。\\n\\n<i>「过去的裁罚已成定局，未来的选择犹在掌握。」\\n「若是不愿命运被一时的罪恶吞尽，还请珍重此刻的光阴。」<\/i>",
      "icon": "Skill_S_Wriothesley_01",
      "promote": {
        "1": {
          "level": 1,
          "costItems": null,
          "coinCost": null,
          "description": [
            "强化斥逐拳伤害|{param1:F1P}普通攻击伤害",
            "消耗生命值|{param2:F1P}生命值上限",
            "持续时间|{param3:F1}秒",
            "冷却时间|{param4:F1}秒",
            "",
            "",
            "",
            "",
            "",
            "",
            "",
            "",
            "",
            "",
            "",
            ""
          ],
          "params": [
            1.43169,
            0.045,
            10,
            16,
            0,
            0,
            0,
            0.4317,
            0,
            0,
            0,
            0,
            0,
            0,
            0,
            0,
            0,
            0,
            0,
            0
          ]
        },
        "2": {
          "level": 2,
          "costItems": {
            "104344": 3,
            "112083": 6
          },
          "coinCost": 12500,
          "description": [
            "强化斥逐拳伤害|{param1:F1P}普通攻击伤害",
            "消耗生命值|{param2:F1P}生命值上限",
            "持续时间|{param3:F1}秒",
            "冷却时间|{param4:F1}秒",
            "",
            "",
            "",
            "",
            "",
            "",
            "",
            "",
            "",
            "",
            "",
            ""
          ],
          "params": [
            1.45755,
            0.045,
            10,
            16,
            0,
            0,
            0,
            0.45755,
            0,
            0,
            0,
            0,
            0,
            0,
            0,
            0,
            0,
            0,
            0,
            0
          ]
        },
        "3": {
          "level": 3,
          "costItems": {
            "104345": 2,
            "112084": 3
          },
          "coinCost": 17500,
          "description": [
            "强化斥逐拳伤害|{param1:F1P}普通攻击伤害",
            "消耗生命值|{param2:F1P}生命值上限",
            "持续时间|{param3:F1}秒",
            "冷却时间|{param4:F1}秒",
            "",
            "",
            "",
            "",
            "",
            "",
            "",
            "",
            "",
            "",
            "",
            ""
          ],
          "params": [
            1.48339,
            0.045,
            10,
            16,
            0,
            0,
            0,
            0.4834,
            0,
            0,
            0,
            0,
            0,
            0,
            0,
            0,
            0,
            0,
            0,
            0
          ]
        },
        "4": {
          "level": 4,
          "costItems": {
            "104345": 4,
            "112084": 4
          },
          "coinCost": 25000,
          "description": [
            "强化斥逐拳伤害|{param1:F1P}普通攻击伤害",
            "消耗生命值|{param2:F1P}生命值上限",
            "持续时间|{param3:F1}秒",
            "冷却时间|{param4:F1}秒",
            "",
            "",
            "",
            "",
            "",
            "",
            "",
            "",
            "",
            "",
            "",
            ""
          ],
          "params": [
            1.517,
            0.045,
            10,
            16,
            0,
            0,
            0,
            0.517,
            0,
            0,
            0,
            0,
            0,
            0,
            0,
            0,
            0,
            0,
            0,
            0
          ]
        },
        "5": {
          "level": 5,
          "costItems": {
            "104345": 6,
            "112084": 6
          },
          "coinCost": 30000,
          "description": [
            "强化斥逐拳伤害|{param1:F1P}普通攻击伤害",
            "消耗生命值|{param2:F1P}生命值上限",
            "持续时间|{param3:F1}秒",
            "冷却时间|{param4:F1}秒",
            "",
            "",
            "",
            "",
            "",
            "",
            "",
            "",
            "",
            "",
            "",
            ""
          ],
          "params": [
            1.54285,
            0.045,
            10,
            16,
            0,
            0,
            0,
            0.54285,
            0,
            0,
            0,
            0,
            0,
            0,
            0,
            0,
            0,
            0,
            0,
            0
          ]
        },
        "6": {
          "level": 6,
          "costItems": {
            "104345": 9,
            "112084": 9
          },
          "coinCost": 37500,
          "description": [
            "强化斥逐拳伤害|{param1:F1P}普通攻击伤害",
            "消耗生命值|{param2:F1P}生命值上限",
            "持续时间|{param3:F1}秒",
            "冷却时间|{param4:F1}秒",
            "",
            "",
            "",
            "",
            "",
            "",
            "",
            "",
            "",
            "",
            "",
            ""
          ],
          "params": [
            1.5687,
            0.045,
            10,
            16,
            0,
            0,
            0,
            0.5687,
            0,
            0,
            0,
            0,
            0,
            0,
            0,
            0,
            0,
            0,
            0,
            0
          ]
        },
        "7": {
          "level": 7,
          "costItems": {
            "104346": 4,
            "112085": 4,
            "113047": 1
          },
          "coinCost": 120000,
          "description": [
            "强化斥逐拳伤害|{param1:F1P}普通攻击伤害",
            "消耗生命值|{param2:F1P}生命值上限",
            "持续时间|{param3:F1}秒",
            "冷却时间|{param4:F1}秒",
            "",
            "",
            "",
            "",
            "",
            "",
            "",
            "",
            "",
            "",
            "",
            ""
          ],
          "params": [
            1.60231,
            0.045,
            10,
            16,
            0,
            0,
            0,
            0.6023,
            0,
            0,
            0,
            0,
            0,
            0,
            0,
            0,
            0,
            0,
            0,
            0
          ]
        },
        "8": {
          "level": 8,
          "costItems": {
            "104346": 6,
            "112085": 6,
            "113047": 1
          },
          "coinCost": 260000,
          "description": [
            "强化斥逐拳伤害|{param1:F1P}普通攻击伤害",
            "消耗生命值|{param2:F1P}生命值上限",
            "持续时间|{param3:F1}秒",
            "冷却时间|{param4:F1}秒",
            "",
            "",
            "",
            "",
            "",
            "",
            "",
            "",
            "",
            "",
            "",
            ""
          ],
          "params": [
            1.63591,
            0.045,
            10,
            16,
            0,
            0,
            0,
            0.63591,
            0,
            0,
            0,
            0,
            0,
            0,
            0,
            0,
            0,
            0,
            0,
            0
          ]
        },
        "9": {
          "level": 9,
          "costItems": {
            "104346": 12,
            "112085": 9,
            "113047": 2
          },
          "coinCost": 450000,
          "description": [
            "强化斥逐拳伤害|{param1:F1P}普通攻击伤害",
            "消耗生命值|{param2:F1P}生命值上限",
            "持续时间|{param3:F1}秒",
            "冷却时间|{param4:F1}秒",
            "",
            "",
            "",
            "",
            "",
            "",
            "",
            "",
            "",
            "",
            "",
            ""
          ],
          "params": [
            1.66952,
            0.045,
            10,
            16,
            0,
            0,
            0,
            0.66952,
            0,
            0,
            0,
            0,
            0,
            0,
            0,
            0,
            0,
            0,
            0,
            0
          ]
        },
        "10": {
          "level": 10,
          "costItems": {
            "104319": 1,
            "104346": 16,
            "112085": 12,
            "113047": 2
          },
          "coinCost": 700000,
          "description": [
            "强化斥逐拳伤害|{param1:F1P}普通攻击伤害",
            "消耗生命值|{param2:F1P}生命值上限",
            "持续时间|{param3:F1}秒",
            "冷却时间|{param4:F1}秒",
            "",
            "",
            "",
            "",
            "",
            "",
            "",
            "",
            "",
            "",
            "",
            ""
          ],
          "params": [
            1.70312,
            0.045,
            10,
            16,
            0,
            0,
            0,
            0.70312,
            0,
            0,
            0,
            0,
            0,
            0,
            0,
            0,
            0,
            0,
            0,
            0
          ]
        },
        "11": {
          "level": 11,
          "costItems": null,
          "coinCost": null,
          "description": [
            "强化斥逐拳伤害|{param1:F1P}普通攻击伤害",
            "消耗生命值|{param2:F1P}生命值上限",
            "持续时间|{param3:F1}秒",
            "冷却时间|{param4:F1}秒",
            "",
            "",
            "",
            "",
            "",
            "",
            "",
            "",
            "",
            "",
            "",
            ""
          ],
          "params": [
            1.73672,
            0.045,
            10,
            16,
            0,
            0,
            0,
            0.73672,
            0,
            0,
            0,
            0,
            0,
            0,
            0,
            0,
            0,
            0,
            0,
            0
          ]
        },
        "12": {
          "level": 12,
          "costItems": null,
          "coinCost": null,
          "description": [
            "强化斥逐拳伤害|{param1:F1P}普通攻击伤害",
            "消耗生命值|{param2:F1P}生命值上限",
            "持续时间|{param3:F1}秒",
            "冷却时间|{param4:F1}秒",
            "",
            "",
            "",
            "",
            "",
            "",
            "",
            "",
            "",
            "",
            "",
            ""
          ],
          "params": [
            1.77033,
            0.045,
            10,
            16,
            0,
            0,
            0,
            0.77033,
            0,
            0,
            0,
            0,
            0,
            0,
            0,
            0,
            0,
            0,
            0,
            0
          ]
        },
        "13": {
          "level": 13,
          "costItems": null,
          "coinCost": null,
          "description": [
            "强化斥逐拳伤害|{param1:F1P}普通攻击伤害",
            "消耗生命值|{param2:F1P}生命值上限",
            "持续时间|{param3:F1}秒",
            "冷却时间|{param4:F1}秒",
            "",
            "",
            "",
            "",
            "",
            "",
            "",
            "",
            "",
            "",
            "",
            ""
          ],
          "params": [
            1.80394,
            0.045,
            10,
            16,
            0,
            0,
            0,
            0.80393,
            0,
            0,
            0,
            0,
            0,
            0,
            0,
            0,
            0,
            0,
            0,
            0
          ]
        },
        "14": {
          "level": 14,
          "costItems": null,
          "coinCost": null,
          "description": [
            "强化斥逐拳伤害|{param1:F1P}普通攻击伤害",
            "消耗生命值|{param2:F1P}生命值上限",
            "持续时间|{param3:F1}秒",
            "冷却时间|{param4:F1}秒",
            "",
            "",
            "",
            "",
            "",
            "",
            "",
            "",
            "",
            "",
            "",
            ""
          ],
          "params": [
            1.83754,
            0.045,
            10,
            16,
            0,
            0,
            0,
            0.83754,
            0,
            0,
            0,
            0,
            0,
            0,
            0,
            0,
            0,
            0,
            0,
            0
          ]
        },
        "15": {
          "level": 15,
          "costItems": null,
          "coinCost": null,
          "description": [
            "强化斥逐拳伤害|{param1:F1P}普通攻击伤害",
            "消耗生命值|{param2:F1P}生命值上限",
            "持续时间|{param3:F1}秒",
            "冷却时间|{param4:F1}秒",
            "",
            "",
            "",
            "",
            "",
            "",
            "",
            "",
            "",
            "",
            "",
            ""
          ],
          "params": [
            1.87115,
            0.045,
            10,
            16,
            0,
            0,
            0,
            0.87115,
            0,
            0,
            0,
            0,
            0,
            0,
            0,
            0,
            0,
            0,
            0,
            0
          ]
        }
      },
      "cooldown": 16,
      "cost": 0
    },
    "3": {
      "type": 1,
      "name": "黑金狼噬",
      "description": "驱动拳套，打出凝聚寒霜的直拳，持续以冰锥冲击前方区域，造成多次<color=#99FFFFFF>冰元素范围伤害<\/color>。\\n\\n<color=#FFD780FF>始基力：荒性<\/color>\\n冰锥冲击结束后，将在敌人的位置降下流涌之刃，造成具有荒性的<color=#99FFFFFF>冰元素伤害<\/color>。\\n\\n<i>总有一些事情，就算是梅洛彼得堡的公爵也会感到无可奈何——例如繁冗的文书工作，琐细的监管职责，或是…小小的友人们在自己拳套上偷偷贴一堆难撕的可爱贴纸的执着。<\/i>",
      "icon": "Skill_E_Wriothesley_01",
      "promote": {
        "1": {
          "level": 1,
          "costItems": null,
          "coinCost": null,
          "description": [
            "技能伤害|{param1:F2P}*5",
            "流涌之刃伤害|{param2:F2P}",
            "冷却时间|{param3:F1}秒",
            "流涌之刃冷却时间|{param5:F1}秒",
            "元素能量|{param4:I}",
            "",
            "",
            "",
            "",
            "",
            "",
            "",
            "",
            "",
            "",
            ""
          ],
          "params": [
            1.272,
            0.424,
            15,
            60,
            10,
            0,
            0,
            0,
            0,
            0,
            0,
            0,
            0,
            0,
            0,
            0,
            0,
            0,
            0,
            0
          ]
        },
        "2": {
          "level": 2,
          "costItems": {
            "104344": 3,
            "112083": 6
          },
          "coinCost": 12500,
          "description": [
            "技能伤害|{param1:F2P}*5",
            "流涌之刃伤害|{param2:F2P}",
            "冷却时间|{param3:F1}秒",
            "流涌之刃冷却时间|{param5:F1}秒",
            "元素能量|{param4:I}",
            "",
            "",
            "",
            "",
            "",
            "",
            "",
            "",
            "",
            "",
            ""
          ],
          "params": [
            1.3674,
            0.4558,
            15,
            60,
            10,
            0,
            0,
            0,
            0,
            0,
            0,
            0,
            0,
            0,
            0,
            0,
            0,
            0,
            0,
            0
          ]
        },
        "3": {
          "level": 3,
          "costItems": {
            "104345": 2,
            "112084": 3
          },
          "coinCost": 17500,
          "description": [
            "技能伤害|{param1:F2P}*5",
            "流涌之刃伤害|{param2:F2P}",
            "冷却时间|{param3:F1}秒",
            "流涌之刃冷却时间|{param5:F1}秒",
            "元素能量|{param4:I}",
            "",
            "",
            "",
            "",
            "",
            "",
            "",
            "",
            "",
            "",
            ""
          ],
          "params": [
            1.4628,
            0.4876,
            15,
            60,
            10,
            0,
            0,
            0,
            0,
            0,
            0,
            0,
            0,
            0,
            0,
            0,
            0,
            0,
            0,
            0
          ]
        },
        "4": {
          "level": 4,
          "costItems": {
            "104345": 4,
            "112084": 4
          },
          "coinCost": 25000,
          "description": [
            "技能伤害|{param1:F2P}*5",
            "流涌之刃伤害|{param2:F2P}",
            "冷却时间|{param3:F1}秒",
            "流涌之刃冷却时间|{param5:F1}秒",
            "元素能量|{param4:I}",
            "",
            "",
            "",
            "",
            "",
            "",
            "",
            "",
            "",
            "",
            ""
          ],
          "params": [
            1.59,
            0.53,
            15,
            60,
            10,
            0,
            0,
            0,
            0,
            0,
            0,
            0,
            0,
            0,
            0,
            0,
            0,
            0,
            0,
            0
          ]
        },
        "5": {
          "level": 5,
          "costItems": {
            "104345": 6,
            "112084": 6
          },
          "coinCost": 30000,
          "description": [
            "技能伤害|{param1:F2P}*5",
            "流涌之刃伤害|{param2:F2P}",
            "冷却时间|{param3:F1}秒",
            "流涌之刃冷却时间|{param5:F1}秒",
            "元素能量|{param4:I}",
            "",
            "",
            "",
            "",
            "",
            "",
            "",
            "",
            "",
            "",
            ""
          ],
          "params": [
            1.6854,
            0.5618,
            15,
            60,
            10,
            0,
            0,
            0,
            0,
            0,
            0,
            0,
            0,
            0,
            0,
            0,
            0,
            0,
            0,
            0
          ]
        },
        "6": {
          "level": 6,
          "costItems": {
            "104345": 9,
            "112084": 9
          },
          "coinCost": 37500,
          "description": [
            "技能伤害|{param1:F2P}*5",
            "流涌之刃伤害|{param2:F2P}",
            "冷却时间|{param3:F1}秒",
            "流涌之刃冷却时间|{param5:F1}秒",
            "元素能量|{param4:I}",
            "",
            "",
            "",
            "",
            "",
            "",
            "",
            "",
            "",
            "",
            ""
          ],
          "params": [
            1.7808,
            0.5936,
            15,
            60,
            10,
            0,
            0,
            0,
            0,
            0,
            0,
            0,
            0,
            0,
            0,
            0,
            0,
            0,
            0,
            0
          ]
        },
        "7": {
          "level": 7,
          "costItems": {
            "104346": 4,
            "112085": 4,
            "113047": 1
          },
          "coinCost": 120000,
          "description": [
            "技能伤害|{param1:F2P}*5",
            "流涌之刃伤害|{param2:F2P}",
            "冷却时间|{param3:F1}秒",
            "流涌之刃冷却时间|{param5:F1}秒",
            "元素能量|{param4:I}",
            "",
            "",
            "",
            "",
            "",
            "",
            "",
            "",
            "",
            "",
            ""
          ],
          "params": [
            1.908,
            0.636,
            15,
            60,
            10,
            0,
            0,
            0,
            0,
            0,
            0,
            0,
            0,
            0,
            0,
            0,
            0,
            0,
            0,
            0
          ]
        },
        "8": {
          "level": 8,
          "costItems": {
            "104346": 6,
            "112085": 6,
            "113047": 1
          },
          "coinCost": 260000,
          "description": [
            "技能伤害|{param1:F2P}*5",
            "流涌之刃伤害|{param2:F2P}",
            "冷却时间|{param3:F1}秒",
            "流涌之刃冷却时间|{param5:F1}秒",
            "元素能量|{param4:I}",
            "",
            "",
            "",
            "",
            "",
            "",
            "",
            "",
            "",
            "",
            ""
          ],
          "params": [
            2.0352,
            0.6784,
            15,
            60,
            10,
            0,
            0,
            0,
            0,
            0,
            0,
            0,
            0,
            0,
            0,
            0,
            0,
            0,
            0,
            0
          ]
        },
        "9": {
          "level": 9,
          "costItems": {
            "104346": 12,
            "112085": 9,
            "113047": 2
          },
          "coinCost": 450000,
          "description": [
            "技能伤害|{param1:F2P}*5",
            "流涌之刃伤害|{param2:F2P}",
            "冷却时间|{param3:F1}秒",
            "流涌之刃冷却时间|{param5:F1}秒",
            "元素能量|{param4:I}",
            "",
            "",
            "",
            "",
            "",
            "",
            "",
            "",
            "",
            "",
            ""
          ],
          "params": [
            2.1624,
            0.7208,
            15,
            60,
            10,
            0,
            0,
            0,
            0,
            0,
            0,
            0,
            0,
            0,
            0,
            0,
            0,
            0,
            0,
            0
          ]
        },
        "10": {
          "level": 10,
          "costItems": {
            "104319": 1,
            "104346": 16,
            "112085": 12,
            "113047": 2
          },
          "coinCost": 700000,
          "description": [
            "技能伤害|{param1:F2P}*5",
            "流涌之刃伤害|{param2:F2P}",
            "冷却时间|{param3:F1}秒",
            "流涌之刃冷却时间|{param5:F1}秒",
            "元素能量|{param4:I}",
            "",
            "",
            "",
            "",
            "",
            "",
            "",
            "",
            "",
            "",
            ""
          ],
          "params": [
            2.2896,
            0.7632,
            15,
            60,
            10,
            0,
            0,
            0,
            0,
            0,
            0,
            0,
            0,
            0,
            0,
            0,
            0,
            0,
            0,
            0
          ]
        },
        "11": {
          "level": 11,
          "costItems": null,
          "coinCost": null,
          "description": [
            "技能伤害|{param1:F2P}*5",
            "流涌之刃伤害|{param2:F2P}",
            "冷却时间|{param3:F1}秒",
            "流涌之刃冷却时间|{param5:F1}秒",
            "元素能量|{param4:I}",
            "",
            "",
            "",
            "",
            "",
            "",
            "",
            "",
            "",
            "",
            ""
          ],
          "params": [
            2.4168,
            0.8056,
            15,
            60,
            10,
            0,
            0,
            0,
            0,
            0,
            0,
            0,
            0,
            0,
            0,
            0,
            0,
            0,
            0,
            0
          ]
        },
        "12": {
          "level": 12,
          "costItems": null,
          "coinCost": null,
          "description": [
            "技能伤害|{param1:F2P}*5",
            "流涌之刃伤害|{param2:F2P}",
            "冷却时间|{param3:F1}秒",
            "流涌之刃冷却时间|{param5:F1}秒",
            "元素能量|{param4:I}",
            "",
            "",
            "",
            "",
            "",
            "",
            "",
            "",
            "",
            "",
            ""
          ],
          "params": [
            2.544,
            0.848,
            15,
            60,
            10,
            0,
            0,
            0,
            0,
            0,
            0,
            0,
            0,
            0,
            0,
            0,
            0,
            0,
            0,
            0
          ]
        },
        "13": {
          "level": 13,
          "costItems": null,
          "coinCost": null,
          "description": [
            "技能伤害|{param1:F2P}*5",
            "流涌之刃伤害|{param2:F2P}",
            "冷却时间|{param3:F1}秒",
            "流涌之刃冷却时间|{param5:F1}秒",
            "元素能量|{param4:I}",
            "",
            "",
            "",
            "",
            "",
            "",
            "",
            "",
            "",
            "",
            ""
          ],
          "params": [
            2.703,
            0.901,
            15,
            60,
            10,
            0,
            0,
            0,
            0,
            0,
            0,
            0,
            0,
            0,
            0,
            0,
            0,
            0,
            0,
            0
          ]
        },
        "14": {
          "level": 14,
          "costItems": null,
          "coinCost": null,
          "description": [
            "技能伤害|{param1:F2P}*5",
            "流涌之刃伤害|{param2:F2P}",
            "冷却时间|{param3:F1}秒",
            "流涌之刃冷却时间|{param5:F1}秒",
            "元素能量|{param4:I}",
            "",
            "",
            "",
            "",
            "",
            "",
            "",
            "",
            "",
            "",
            ""
          ],
          "params": [
            2.862,
            0.954,
            15,
            60,
            10,
            0,
            0,
            0,
            0,
            0,
            0,
            0,
            0,
            0,
            0,
            0,
            0,
            0,
            0,
            0
          ]
        },
        "15": {
          "level": 15,
          "costItems": null,
          "coinCost": null,
          "description": [
            "技能伤害|{param1:F2P}*5",
            "流涌之刃伤害|{param2:F2P}",
            "冷却时间|{param3:F1}秒",
            "流涌之刃冷却时间|{param5:F1}秒",
            "元素能量|{param4:I}",
            "",
            "",
            "",
            "",
            "",
            "",
            "",
            "",
            "",
            "",
            ""
          ],
          "params": [
            3.021,
            1.007,
            15,
            60,
            10,
            0,
            0,
            0,
            0,
            0,
            0,
            0,
            0,
            0,
            0,
            0,
            0,
            0,
            0,
            0
          ]
        }
      },
      "cooldown": 15,
      "cost": 60
    },
    "4": {
      "type": 2,
      "name": "公理终有辩诉之日",
      "description": "莱欧斯利的生命值低于60%时，将获得「恩典之诫」，使下次<color=#FFD780FF>普通攻击·迅烈倾霜拳<\/color>的重击强化为惩戒·凌跃拳：不消耗体力，造成的伤害提升50%，并在命中后为莱欧斯利恢复生命值，回复量相当于莱欧斯利生命值上限的30%。\\n每5秒至多通过这种方式获得一次「恩典之诫」效果。",
      "icon": "UI_Talent_S_Wriothesley_05"
    },
    "5": {
      "type": 2,
      "name": "罪业终有报偿之时",
      "description": "莱欧斯利的当前生命值提升或降低时，若莱欧斯利处于<color=#FFD780FF>冰牙突驰<\/color>的寒烈的惩裁状态下，寒烈的惩裁将获得一层「检偿之敕」效果，该效果至多叠加至5层，每层使莱欧斯利的攻击力提升6%。",
      "icon": "UI_Talent_S_Wriothesley_06"
    },
    "6": {
      "type": 2,
      "name": "公爵的恩馈",
      "description": "合成武器突破素材时，有10%概率获得2倍产出。",
      "icon": "UI_Talent_Combine_Weapon_Double"
    }
  },
  "constellation": {
    "0": {
      "name": "予行恶者以惩惧",
      "description": "固有天赋「公理终有辩诉之日」的「恩典之诫」转变为：\\n莱欧斯利的生命值低于60%，或在<color=#FFD780FF>冰牙突驰<\/color>的寒烈的惩裁状态持续期间，斥逐拳的第五段攻击命中时，将获得「恩典之诫」，每2.5秒至多获得一次「恩典之诫」效果。\\n\\n此外，惩戒·凌跃拳获得以下强化：\\n·造成的伤害提升进一步提升至200%；\\n·命中时，若处于寒烈的惩裁状态下，该状态的持续时间延长4秒，在一次寒烈的惩裁状态持续期间，至多通过这种方式延长一次。\\n\\n需要解锁固有天赋「公理终有辩诉之日」。",
      "extraData": null,
      "icon": "UI_Talent_S_Wriothesley_01"
    },
    "1": {
      "name": "予骄暴者以镣锁",
      "description": "施放<color=#FFD780FF>黑金狼噬<\/color>时，固有天赋「罪业终有报偿之时」的每层「检偿之敕」效果都将使造成的伤害提升40%。\\n需要解锁固有天赋「罪业终有报偿之时」。",
      "extraData": null,
      "icon": "UI_Talent_S_Wriothesley_02"
    },
    "2": {
      "name": "予婪诈者以谴罚",
      "description": "<color=#FFD780FF>普通攻击·迅烈倾霜拳<\/color>的技能等级提高3级。\\n至多提升至15级。",
      "extraData": {
        "addTalentExtraLevel": {
          "talentType": "AvatarSkill",
          "talentIndex": 1,
          "extraLevel": 3
        }
      },
      "icon": "UI_Talent_U_Wriothesley_01"
    },
    "3": {
      "name": "予贞苦者以拯赎",
      "description": "惩戒·凌跃拳为莱欧斯利恢复生命值的回复量提升为50%生命值上限，需要解锁固有天赋「公理终有辩诉之日」。\\n此外，莱欧斯利受到治疗时，若此次治疗回复量溢出，将根据莱欧斯利是否处于当前场上产生不同的效果：处于当前场上时，莱欧斯利的攻击速度提升20%，持续4秒；处于队伍后台时，队伍中所有自己的角色攻击速度提升10%，持续6秒。上述这两种攻击速度提升效果无法叠加。",
      "extraData": null,
      "icon": "UI_Talent_S_Wriothesley_03"
    },
    "4": {
      "name": "予冤诉者以怜恕",
      "description": "<color=#FFD780FF>黑金狼噬<\/color>的技能等级提高3级。\\n至多提升至15级。",
      "extraData": {
        "addTalentExtraLevel": {
          "talentType": "AvatarSkill",
          "talentIndex": 9,
          "extraLevel": 3
        }
      },
      "icon": "UI_Talent_U_Wriothesley_02"
    },
    "5": {
      "name": "予无罪者以念抚",
      "description": "惩戒·凌跃拳的暴击率提升10%，暴击伤害提升80%，并能够额外生成冰锥，造成原本100%的<color=#99FFFFFF>冰元素伤害<\/color>，通过这种方式造成的伤害视为重击伤害。\\n需要解锁固有天赋「公理终有辩诉之日」。",
      "extraData": null,
      "icon": "UI_Talent_S_Wriothesley_04"
    }
  }
}