{
  "id": 25040101,
  "name": "盗宝团·「大姐头」",
  "type": "其他人类势力",
  "icon": "UI_MonsterIcon_Thoarder_Female_Hatchet_01",
  "route": "Treasure Hoarders: Boss",
  "title": "盗宝团·「大姐头」",
  "specialName": "变化万端",
  "description": "（test）待IP补充",
  "entries": {
    "25040101": {
      "id": 25040101,
      "type": "MONSTER_ORDINARY",
      "affix": null,
      "hpDrops": [
        {
          "id": 22010010,
          "hpPercent": 75
        },
        {
          "id": 22010010,
          "hpPercent": 50
        },
        {
          "id": 22010010,
          "hpPercent": 25
        }
      ],
      "prop": [
        {
          "propType": "FIGHT_PROP_BASE_HP",
          "initValue": 32.6016,
          "type": "GROW_CURVE_HP"
        },
        {
          "propType": "FIGHT_PROP_BASE_ATTACK",
          "initValue": 25.12,
          "type": "GROW_CURVE_ATTACK"
        },
        {
          "propType": "FIGHT_PROP_BASE_DEFENSE",
          "initValue": 500,
          "type": "GROW_CURVE_DEFENSE"
        }
      ],
      "resistance": {
        "fireSubHurt": 0.1,
        "grassSubHurt": 0.1,
        "waterSubHurt": 0.1,
        "elecSubHurt": 0.1,
        "windSubHurt": 0.1,
        "iceSubHurt": 0.1,
        "rockSubHurt": 0.1,
        "physicalSubHurt": -0.2
      },
      "reward": null
    },
    "25040102": {
      "id": 25040102,
      "type": "MONSTER_ORDINARY",
      "affix": [
        {
          "name": "黑貉队 烟花技能效果",
          "description": "影响黑貉队是否会对2.4打捞活动的烟花有反应",
          "abilityName": [
            "MonsterAffix_Activity_Thoarder_Elite_Tag"
          ],
          "isCommon": true
        }
      ],
      "hpDrops": [
        {
          "id": 22010020,
          "hpPercent": 66
        },
        {
          "id": 22010020,
          "hpPercent": 33
        }
      ],
      "prop": [
        {
          "propType": "FIGHT_PROP_BASE_HP",
          "initValue": 95.088,
          "type": "GROW_CURVE_HP_2"
        },
        {
          "propType": "FIGHT_PROP_BASE_ATTACK",
          "initValue": 37.68,
          "type": "GROW_CURVE_ATTACK"
        },
        {
          "propType": "FIGHT_PROP_BASE_DEFENSE",
          "initValue": 500,
          "type": "GROW_CURVE_DEFENSE"
        }
      ],
      "resistance": {
        "fireSubHurt": 0.1,
        "grassSubHurt": 0.1,
        "waterSubHurt": 0.1,
        "elecSubHurt": 0.1,
        "windSubHurt": 0.1,
        "iceSubHurt": 0.1,
        "rockSubHurt": 0.1,
        "physicalSubHurt": -0.2
      },
      "reward": null
    },
    "25040103": {
      "id": 25040103,
      "type": "MONSTER_ORDINARY",
      "affix": null,
      "hpDrops": [
        {
          "id": 22010020,
          "hpPercent": 66
        },
        {
          "id": 22010020,
          "hpPercent": 33
        }
      ],
      "prop": [
        {
          "propType": "FIGHT_PROP_BASE_HP",
          "initValue": 95.088,
          "type": "GROW_CURVE_HP_2"
        },
        {
          "propType": "FIGHT_PROP_BASE_ATTACK",
          "initValue": 37.68,
          "type": "GROW_CURVE_ATTACK"
        },
        {
          "propType": "FIGHT_PROP_BASE_DEFENSE",
          "initValue": 500,
          "type": "GROW_CURVE_DEFENSE"
        }
      ],
      "resistance": {
        "fireSubHurt": 0.1,
        "grassSubHurt": 0.1,
        "waterSubHurt": 0.1,
        "elecSubHurt": 0.1,
        "windSubHurt": 0.1,
        "iceSubHurt": 0.1,
        "rockSubHurt": 0.1,
        "physicalSubHurt": -0.2
      },
      "reward": null
    }
  },
  "tips": null
}