{
  "id": 26050601,
  "name": "深海龙蜥·原种",
  "type": "异种魔兽",
  "icon": "UI_MonsterIcon_Drake_Deepsea_Water",
  "route": "Primordial Bathysmal Vishap",
  "title": "深海龙蜥·原种",
  "specialName": "盘踞深海的水栖猛兽",
  "description": "生活在海渊之下的龙蜥。\\n它们曾经是海渊之下的支配种族——其实在更加久远的过去，龙们就是这个世界的支配者。曾经的七王被高天之力打败，相继凋零了。",
  "entries": {
    "26050601": {
      "id": 26050601,
      "type": "MONSTER_ORDINARY",
      "affix": null,
      "hpDrops": [
        {
          "id": 22010012,
          "hpPercent": 75
        },
        {
          "id": 22010012,
          "hpPercent": 50
        },
        {
          "id": 22010012,
          "hpPercent": 25
        }
      ],
      "prop": [
        {
          "propType": "FIGHT_PROP_BASE_HP",
          "initValue": 108.672,
          "type": "GROW_CURVE_HP_2"
        },
        {
          "propType": "FIGHT_PROP_BASE_ATTACK",
          "initValue": 50.24,
          "type": "GROW_CURVE_ATTACK"
        },
        {
          "propType": "FIGHT_PROP_BASE_DEFENSE",
          "initValue": 500,
          "type": "GROW_CURVE_DEFENSE"
        }
      ],
      "resistance": {
        "fireSubHurt": 0.1,
        "grassSubHurt": 0.1,
        "waterSubHurt": 0.3,
        "elecSubHurt": 0.1,
        "windSubHurt": 0.1,
        "iceSubHurt": 0.1,
        "rockSubHurt": 0.1,
        "physicalSubHurt": 0.3
      },
      "reward": {
        "202": {
          "rank": 3,
          "icon": "UI_ItemIcon_202"
        },
        "112041": {
          "rank": 2,
          "icon": "UI_ItemIcon_112041",
          "count": "5.2526"
        },
        "112042": {
          "rank": 3,
          "icon": "UI_ItemIcon_112042",
          "count": "1.4006"
        },
        "112043": {
          "rank": 4,
          "icon": "UI_ItemIcon_112043",
          "count": "0.3502"
        },
        "400022": {
          "rank": 3,
          "icon": "UI_RelicIcon_10005_4"
        },
        "400023": {
          "rank": 4,
          "icon": "UI_RelicIcon_10005_4"
        },
        "400032": {
          "rank": 3,
          "icon": "UI_RelicIcon_10007_4"
        },
        "400033": {
          "rank": 4,
          "icon": "UI_RelicIcon_10007_4"
        },
        "400042": {
          "rank": 3,
          "icon": "UI_RelicIcon_10009_4"
        },
        "400043": {
          "rank": 4,
          "icon": "UI_RelicIcon_10009_4"
        },
        "400062": {
          "rank": 3,
          "icon": "UI_RelicIcon_10013_4"
        }
      }
    }
  },
  "tips": {
    "300401": {
      "images": [
        "UI_Tutorial_122c"
      ],
      "description": "蛰伏于漆黑深水中的掠食者。应对着深海中的未知力量，或许也演化出了水元素以外的变体…面对强敌时，会使出威力强大的「涤魔喷吐」。命中角色后，角色将<color=#FFE14BFF>流失一定元素能量<\/color>。若角色的元素能量不足，将<color=#FFE14BFF>损失生命值<\/color>。"
    }
  }
}