{
  "id": 15405,
  "rank": 4,
  "type": "弓",
  "name": "弓藏",
  "description": "布满锈迹的铁造大弓，一般人根本拿不动，遑论引弓放矢。",
  "icon": "UI_EquipIcon_Bow_Recluse",
  "storyId": 195405,
  "affix": {
    "115405": {
      "name": "速射弓斗",
      "upgrade": {
        "0": "普通攻击造成的伤害提升<color=#99FFFFFF>40%<\/color>，重击造成的伤害下降10%。",
        "1": "普通攻击造成的伤害提升<color=#99FFFFFF>50%<\/color>，重击造成的伤害下降10%。",
        "2": "普通攻击造成的伤害提升<color=#99FFFFFF>60%<\/color>，重击造成的伤害下降10%。",
        "3": "普通攻击造成的伤害提升<color=#99FFFFFF>70%<\/color>，重击造成的伤害下降10%。",
        "4": "普通攻击造成的伤害提升<color=#99FFFFFF>80%<\/color>，重击造成的伤害下降10%。"
      }
    }
  },
  "route": "Rust",
  "upgrade": {
    "awakenCost": [
      1000,
      2000,
      4000,
      8000
    ],
    "prop": [
      {
        "propType": "FIGHT_PROP_BASE_ATTACK",
        "initValue": 42.401,
        "type": "GROW_CURVE_ATTACK_201"
      },
      {
        "propType": "FIGHT_PROP_ATTACK_PERCENT",
        "initValue": 0.09,
        "type": "GROW_CURVE_CRITICAL_201"
      }
    ],
    "promote": [
      {
        "unlockMaxLevel": 20,
        "promoteLevel": 0
      },
      {
        "promoteLevel": 1,
        "costItems": {
          "112005": 2,
          "112029": 3,
          "114013": 3
        },
        "coinCost": 5000,
        "addProps": {
          "FIGHT_PROP_BASE_ATTACK": 25.9,
          "FIGHT_PROP_CRITICAL": 0,
          "FIGHT_PROP_CRITICAL_HURT": 0,
          "FIGHT_PROP_CHARGE_EFFICIENCY": 0,
          "FIGHT_PROP_ELEMENT_MASTERY": 0
        },
        "unlockMaxLevel": 40,
        "requiredPlayerLevel": 15
      },
      {
        "promoteLevel": 2,
        "costItems": {
          "112005": 8,
          "112029": 12,
          "114014": 3
        },
        "coinCost": 15000,
        "addProps": {
          "FIGHT_PROP_BASE_ATTACK": 51.9,
          "FIGHT_PROP_CRITICAL": 0,
          "FIGHT_PROP_CRITICAL_HURT": 0,
          "FIGHT_PROP_CHARGE_EFFICIENCY": 0,
          "FIGHT_PROP_ELEMENT_MASTERY": 0
        },
        "unlockMaxLevel": 50,
        "requiredPlayerLevel": 25
      },
      {
        "promoteLevel": 3,
        "costItems": {
          "112006": 6,
          "112030": 6,
          "114014": 6
        },
        "coinCost": 20000,
        "addProps": {
          "FIGHT_PROP_BASE_ATTACK": 77.8,
          "FIGHT_PROP_CRITICAL": 0,
          "FIGHT_PROP_CRITICAL_HURT": 0,
          "FIGHT_PROP_CHARGE_EFFICIENCY": 0,
          "FIGHT_PROP_ELEMENT_MASTERY": 0
        },
        "unlockMaxLevel": 60,
        "requiredPlayerLevel": 30
      },
      {
        "promoteLevel": 4,
        "costItems": {
          "112006": 9,
          "112030": 12,
          "114015": 3
        },
        "coinCost": 30000,
        "addProps": {
          "FIGHT_PROP_BASE_ATTACK": 103.7,
          "FIGHT_PROP_CRITICAL": 0,
          "FIGHT_PROP_CRITICAL_HURT": 0,
          "FIGHT_PROP_CHARGE_EFFICIENCY": 0,
          "FIGHT_PROP_ELEMENT_MASTERY": 0
        },
        "unlockMaxLevel": 70,
        "requiredPlayerLevel": 35
      },
      {
        "promoteLevel": 5,
        "costItems": {
          "112007": 6,
          "112031": 9,
          "114015": 6
        },
        "coinCost": 35000,
        "addProps": {
          "FIGHT_PROP_BASE_ATTACK": 129.7,
          "FIGHT_PROP_CRITICAL": 0,
          "FIGHT_PROP_CRITICAL_HURT": 0,
          "FIGHT_PROP_CHARGE_EFFICIENCY": 0,
          "FIGHT_PROP_ELEMENT_MASTERY": 0
        },
        "unlockMaxLevel": 80,
        "requiredPlayerLevel": 40
      },
      {
        "promoteLevel": 6,
        "costItems": {
          "112007": 12,
          "112031": 18,
          "114016": 4
        },
        "coinCost": 45000,
        "addProps": {
          "FIGHT_PROP_BASE_ATTACK": 155.60001,
          "FIGHT_PROP_CRITICAL": 0,
          "FIGHT_PROP_CRITICAL_HURT": 0,
          "FIGHT_PROP_CHARGE_EFFICIENCY": 0,
          "FIGHT_PROP_ELEMENT_MASTERY": 0
        },
        "unlockMaxLevel": 90,
        "requiredPlayerLevel": 50
      }
    ]
  },
  "ascension": {
    "112005": 1,
    "112006": 2,
    "112007": 3,
    "112029": 2,
    "112030": 3,
    "112031": 4,
    "114013": 2,
    "114014": 3,
    "114015": 4,
    "114016": 5
  }
}